Workbook

Sheet GK Main Data
A1: id | B1: post_type | C1: langu | D1: title | E1: category | F1: Category Decode | G1: subcategory | H1: SubCategory Decode | I1: section | J1: Section Decode | K1: image | L1: image_link | M1: documnet_link | N1: description | O1: created | P1: updated
A2: 73 | B2: GK | C2: English | D2: Abinash Bhattacharjee: Ghadar Patriot and Cellular Jail Freedom Fighter | E2: 1 | F2: =vlookup(E2,Category_ID!A:B,2,0) -> Indian History | G2: 3 | H2: =vlookup(G2,Sub_Category_ID!A:C,3,0) -> Modern History | I2: 39 | J2: =vlookup(I2,Section!A:D,4,0) -> Freedom Fighters and Their Contributions | K2: ddb7283023cc791ce80cb0e8ccc10815.jpg | M2: 1757059501_Abinash Chandra Bhattacharjee.pdf | N2: Abinash Chandra Bhattacharjee was a revolutionary associated with India’s early armed struggle for independence. Closely linked to the Jugantar Party and the Ghadar Movement, he was arrested for seditious activities and sentenced to Kala Pani at the Cellular Jail. He symbolizes the sacrifices made by young revolutionaries during the colonial era who fought British oppression through radical means. | O2: 0000-00-00 00:00:00 | P2: 0000-00-00 00:00:00
A3: 74 | B3: GK | C3: English | D3: Ullaskar Dutta: Revolutionary Bomb Maker Deported to Cellular Jail, Kalapani | F3: =vlookup(E3,Category_ID!A:B,2,0) -> #N/A | H3: =vlookup(G3,Sub_Category_ID!A:C,3,0) -> #N/A | J3: =vlookup(I3,Section!A:D,4,0) -> #N/A | K3: fdc645dcc65a9a071d66c06708f64be5.jpg | M3: 1757063597_Ullaskar Dutta.pdf | N3: Ullaskar Dutta was a prominent revolutionary associated with the Anushilan Samiti. Arrested in 1908 in the Alipore Bomb Case, he was sentenced to life and deported to the Cellular Jail in the Andamans. His incarceration saw extreme torture, leading to a mental breakdown. He was later released in 1915 and became a vocal critic of British colonial repression.\r\n | O3: 0000-00-00 00:00:00 | P3: 0000-00-00 00:00:00
A4: 75 | B4: GK | C4: English | D4: Indu Bhushan Roy: Forgotten Revolutionary Martyr of Cellular Jail History | F4: =vlookup(E4,Category_ID!A:B,2,0) -> #N/A | H4: =vlookup(G4,Sub_Category_ID!A:C,3,0) -> #N/A | J4: =vlookup(I4,Section!A:D,4,0) -> #N/A | K4: 402d1aa53aaa434c4de03d63b46cedf4.jpg | M4: 1757064614_Indu Bhushan Roy.pdf | N4: Indu Bhushan Roy was a valiant Bengali revolutionary linked with the Anushilan Samiti. Arrested for his involvement in armed resistance, he was deported to the infamous Cellular Jail in the Andamans. Tortured severely, he died under suspicious circumstances—likely suicide or custodial killing—becoming one of the earliest martyrs of Kalapani, symbolizing the brutality faced by political prisoners.\r\n | O4: 0000-00-00 00:00:00 | P4: 0000-00-00 00:00:00
A5: 76 | B5: GK | C5: English | D5: Trailokyanath Chakraborty: Voice Against Colonial Rule and Injustice | F5: =vlookup(E5,Category_ID!A:B,2,0) -> #N/A | H5: =vlookup(G5,Sub_Category_ID!A:C,3,0) -> #N/A | J5: =vlookup(I5,Section!A:D,4,0) -> #N/A | K5: b64688ee3f448233b303345726f5233f.jpg | M5: 1757064936_Trailokyanath Chakraborty.pdf | N5: Trailokyanath Chakraborty was a prominent Bengali revolutionary and freedom fighter associated with the Anushilan Samiti. Arrested multiple times by the British, he was deported to the Cellular Jail in the Andamans. Even after release, he remained active in the nationalist struggle. His life symbolized relentless resistance, ideological clarity, and sacrifice in the fight for India\'s independence.\r\n | O5: 0000-00-00 00:00:00 | P5: 0000-00-00 00:00:00
A6: 77 | B6: GK | C6: English | D6: Vinayak Damodar (Veer) Savarkar: Hindutva theorist, revolutionary, writer, and Cellular Jail prisoner | F6: =vlookup(E6,Category_ID!A:B,2,0) -> #N/A | H6: =vlookup(G6,Sub_Category_ID!A:C,3,0) -> #N/A | J6: =vlookup(I6,Section!A:D,4,0) -> #N/A | K6: 55c34eeb912e92cd21fecfd2accaa871.jpeg | M6: 1757065529_Vinayak Damodar (Veer) Savarkar.pdf | N6: Vinayak Damodar Savarkar (1883–1966) was a revolutionary, poet, and political ideologue who pioneered the concept of Hindutva. He founded Abhinav Bharat Society and influenced the armed struggle for India’s independence. Imprisoned in the Andamans, later led Hindu Mahasabha. Though controversial, he inspired generations with his writings and fearless resistance to colonial rule. | O6: 0000-00-00 00:00:00 | P6: 0000-00-00 00:00:00
A7: 78 | B7: GK | C7: English | D7: Bhai Parmanand: Arya Samaj missionary turned Ghadar revolutionary and Hindu Mahasabha leader | F7: =vlookup(E7,Category_ID!A:B,2,0) -> #N/A | H7: =vlookup(G7,Sub_Category_ID!A:C,3,0) -> #N/A | J7: =vlookup(I7,Section!A:D,4,0) -> #N/A | K7: d807de3df93081d81a481a904ace16ba.jpg | M7: 1757066018_Bhai Parmanand.pdf | N7: Bhai Parmanand (4 November 1876 – 8 December 1947) was a Mohyal Brahmin Arya Samajist from Punjab who travelled abroad as a missionary and connected with Lala Hardayal. A founding member of the Ghadar Party, he co-led the 1915 Lahore Conspiracy. Sentenced to death, later commuted to life, spent years in Andamans, launched a prolonged hunger strike, and later led Hindu Mahasabha.\r\n | O7: 0000-00-00 00:00:00 | P7: 0000-00-00 00:00:00
A8: 79 | B8: GK | C8: English | D8: Shambhu Nath Azad: Chambal-born revolutionary, hunger striker, daring bank raid leader | F8: =vlookup(E8,Category_ID!A:B,2,0) -> #N/A | H8: =vlookup(G8,Sub_Category_ID!A:C,3,0) -> #N/A | J8: =vlookup(I8,Section!A:D,4,0) -> #N/A | K8: 8f15513885e66033d803ad5e48eb4bd2.jpg | M8: 1757066603_Shambhu Nath Azad.pdf | N8: Shambhu Nath Azad, born in Agra (Kachhaura Ghat, Chambal region), joined Naujawan Bharat Sabha and Anushilan Samiti in his teens. Trained in guerrilla tactics, he formed a clandestine group (“Dasta”) in 1932 after release from jail. He orchestrated the daring Udhagamandalam (Ooty) bank robbery in April 1933 and endured long jail terms in Cellular Jail, including hunger strikes.\r\n | O8: 0000-00-00 00:00:00 | P8: 0000-00-00 00:00:00
A9: 80 | B9: GK | C9: English | D9: Upendra Nath Banerjee: Revolutionary Transported to Andamans for Sedition | E9: 1 | F9: =vlookup(E9,Category_ID!A:B,2,0) -> Indian History | G9: 3 | H9: =vlookup(G9,Sub_Category_ID!A:C,3,0) -> Modern History | I9: 39 | J9: =vlookup(I9,Section!A:D,4,0) -> Freedom Fighters and Their Contributions | K9: 2f45d6f666f0ab2b713f5e6b717cc8ca.jpg | M9: 1757067929_Upendra Nath Banerjee.pdf | N9: Upendra Nath Banerjee was a courageous revolutionary associated with the Anushilan Samiti. Arrested for his role in anti-British conspiracies, he was sentenced to Kala Pani—transportation for life to the Cellular Jail in the Andaman Islands. He represents a generation of patriots who dared to defy British colonialism through radical activism and underground movements.\r\n | O9: 0000-00-00 00:00:00 | P9: 0000-00-00 00:00:00
A10: 81 | B10: GK | C10: English | D10: Barindra Ghosh: Revolutionary Journalist and Alipore Bomb Case Accused | E10: 1 | F10: =vlookup(E10,Category_ID!A:B,2,0) -> Indian History | G10: 3 | H10: =vlookup(G10,Sub_Category_ID!A:C,3,0) -> Modern History | I10: 39 | J10: =vlookup(I10,Section!A:D,4,0) -> Freedom Fighters and Their Contributions | K10: 422135244a3242ff423aec17db4b8151.jpg | M10: 1757068265_Barindra Kumar Ghosh.pdf | N10: Barindra Kumar Ghosh was a key figure in India’s revolutionary nationalist movement and the younger brother of philosopher Sri Aurobindo. He founded the revolutionary journal Jugantar and was implicated in the Alipore Bomb Case. Initially sentenced to death, his punishment was commuted to life imprisonment in the Andaman’s Cellular Jail, marking his place in history among the notable Kala Pani convicts.\r\n | O10: 0000-00-00 00:00:00 | P10: 0000-00-00 00:00:00
A11: 82 | B11: GK | C11: English | D11: Mohit Moitra: Martyr of Cellular Jail’s Historic 1933 Hunger Strike | E11: 1 | F11: =vlookup(E11,Category_ID!A:B,2,0) -> Indian History | G11: 3 | H11: =vlookup(G11,Sub_Category_ID!A:C,3,0) -> Modern History | I11: 39 | J11: =vlookup(I11,Section!A:D,4,0) -> Freedom Fighters and Their Contributions | K11: 70dfddee4571ae1fcdaf5f556579d4b4.jpg | M11: 1757068791_Mohit Moitra.pdf | N11: Mohit Moitra was a Bengali revolutionary and a member of the Jugantar group. Arrested for his anti-British activities, he was deported to the Cellular Jail. In 1933, he joined a hunger strike to protest the inhumane treatment of political prisoners. He died after being forcibly fed by jail authorities, becoming one of the three martyrs of that strike.\r\n | O11: 0000-00-00 00:00:00 | P11: 0000-00-00 00:00:00
A12: 83 | B12: GK | C12: English | D12: Mohan Kishore Namadas: Revolutionary Martyr of Cellular Jail Hunger Strike | E12: 1 | F12: =vlookup(E12,Category_ID!A:B,2,0) -> Indian History | G12: 3 | H12: =vlookup(G12,Sub_Category_ID!A:C,3,0) -> Modern History | I12: 39 | J12: =vlookup(I12,Section!A:D,4,0) -> Freedom Fighters and Their Contributions | K12: ae2dfbb25e06bafb627e0a3fed83e921.jpg | M12: 1757069671_Mohan Kishore Namadas.pdf | N12: Mohan Kishore Namadas, a Bengali revolutionary, was a key member of the Anushilan Samiti. Arrested for revolutionary activities, he was sentenced to life imprisonment and deported to the Cellular Jail. In 1933, during a hunger strike for better treatment of political prisoners, he died due to brutal forced feeding. His martyrdom highlighted British cruelty in penal colonies.\r\n | O12: 0000-00-00 00:00:00 | P12: 0000-00-00 00:00:00
A13: 84 | B13: GK | C13: English | D13: Mahavir Singh: Martyr Who Defied British Rule in Cellular Jail | E13: 1 | F13: =vlookup(E13,Category_ID!A:B,2,0) -> Indian History | G13: 3 | H13: =vlookup(G13,Sub_Category_ID!A:C,3,0) -> Modern History | I13: 39 | J13: =vlookup(I13,Section!A:D,4,0) -> Freedom Fighters and Their Contributions | K13: 6d5a8fe51ebaf2164a78891b0e9d06cb.jpg | M13: 1757071092_Mahavir Singh.pdf | N13: Mahavir Singh, a courageous revolutionary from Uttar Pradesh, joined the Hindustan Socialist Republican Association (HSRA). He was imprisoned and sent to the Cellular Jail in the Andamans. While protesting against the brutal treatment of fellow prisoners, he undertook a hunger strike. He died during forced feeding, becoming one of the first martyrs of Cellular Jail.\r\n | O13: 0000-00-00 00:00:00 | P13: 0000-00-00 00:00:00
A14: 85 | B14: GK | C14: English | D14: Khudiram Bose: Young Revolutionary, Symbol of Courage and Sacrifice | E14: 1 | F14: =vlookup(E14,Category_ID!A:B,2,0) -> Indian History | G14: 3 | H14: =vlookup(G14,Sub_Category_ID!A:C,3,0) -> Modern History | I14: 39 | J14: =vlookup(I14,Section!A:D,4,0) -> Freedom Fighters and Their Contributions | K14: 7344218a1ddddb2d945fd211ec5f1ae3.jpg | M14: 1757071333_Khudiram Bosh.pdf | N14: Khudiram Bose was one of India’s youngest freedom fighters, martyred at just 18. Born in Midnapore in 1889, he joined the revolutionary Anushilan Samiti. In the Muzaffarpur Conspiracy Case, he attempted to assassinate a British judge but mistakenly killed two women. Captured and hanged in 1908, he remains a symbol of courage, with his legacy honored across India.\r\n | O14: 0000-00-00 00:00:00 | P14: 0000-00-00 00:00:00
A15: 86 | B15: GK | C15: English | D15: Bhagat Singh: Revolutionary Icon Who Challenged British Rule with Courage | E15: 1 | F15: =vlookup(E15,Category_ID!A:B,2,0) -> Indian History | G15: 3 | H15: =vlookup(G15,Sub_Category_ID!A:C,3,0) -> Modern History | I15: 39 | J15: =vlookup(I15,Section!A:D,4,0) -> Freedom Fighters and Their Contributions | K15: 788ef6588d28d28962e494f858e953ae.jpg | M15: 1757072129_Bhagat Singh.pdf | N15: Bhagat Singh was a socialist revolutionary who opposed British colonialism through radical means. Influenced by Marxism and nationalism, he participated in significant acts like the Assembly bombing and Saunders\' assassination. Hanged at 23, he became a martyr. His legacy inspires youth, symbolizing bravery, ideology-driven action, and ultimate sacrifice for India’s freedom.\r\n | O15: 0000-00-00 00:00:00 | P15: 0000-00-00 00:00:00
A16: 87 | B16: GK | C16: English | D16: Shivaram Rajguru: Brave Revolutionary and Martyr of India’s Freedom Struggle | E16: 1 | F16: =vlookup(E16,Category_ID!A:B,2,0) -> Indian History | G16: 3 | H16: =vlookup(G16,Sub_Category_ID!A:C,3,0) -> Modern History | I16: 39 | J16: =vlookup(I16,Section!A:D,4,0) -> Freedom Fighters and Their Contributions | K16: d5b68ffd2c68b4efafabe099a7172cf2.jpg | M16: 1757072632_Shivaram Rajguru.pdf | N16: Shivaram Rajguru was a fearless revolutionary from Maharashtra who fought against British rule. As a member of HSRA, he participated in the assassination of British officer John Saunders alongside Bhagat Singh and Sukhdev. A firm believer in armed resistance, Rajguru was hanged on 23 March 1931. He is remembered as a symbol of youthful sacrifice and patriotism.\r\n | O16: 0000-00-00 00:00:00 | P16: 0000-00-00 00:00:00
A17: 88 | B17: GK | C17: English | D17: Sukhdev Thapar: Committed Revolutionary and Martyr of India’s Freedom Struggle | E17: 1 | F17: =vlookup(E17,Category_ID!A:B,2,0) -> Indian History | G17: 3 | H17: =vlookup(G17,Sub_Category_ID!A:C,3,0) -> Modern History | I17: 39 | J17: =vlookup(I17,Section!A:D,4,0) -> Freedom Fighters and Their Contributions | K17: 0433c45fdd396b4371b821c486b16e6d.jpg | M17: 1757072988_Sukhdev Thapar.pdf | N17: Sukhdev Thapar was a dedicated revolutionary from Punjab who played a key role in India’s freedom struggle. As a senior member of HSRA, he helped organize revolutionary cells and participated in the Saunders assassination. Known for his discipline and leadership, he was executed with Bhagat Singh and Rajguru on 23 March 1931. His martyrdom remains an inspiration.\r\n | O17: 0000-00-00 00:00:00 | P17: 0000-00-00 00:00:00
A18: 89 | B18: GK | C18: English | D18: Ram Prasad Bismil: Poet Revolutionary Behind Kakori Conspiracy Against British Rule | E18: 1 | F18: =vlookup(E18,Category_ID!A:B,2,0) -> Indian History | G18: 3 | H18: =vlookup(G18,Sub_Category_ID!A:C,3,0) -> Modern History | I18: 39 | J18: =vlookup(I18,Section!A:D,4,0) -> Freedom Fighters and Their Contributions | K18: f1a81f2838d15bf27ab7fcfaffad95d2.jpg | M18: 1757073299_Ram Prasad Bismil.pdf | N18: Ram Prasad Bismil was a prominent revolutionary, poet, and freedom fighter who fought British colonialism through armed struggle. He co-founded the Hindustan Republican Association (HRA) and led the famous Kakori Train Robbery of 1925. A powerful orator and nationalist poet, Bismil was executed in 1927, leaving behind a legacy of patriotism and poetic resistance.\r\n | O18: 0000-00-00 00:00:00 | P18: 0000-00-00 00:00:00
A19: 90 | B19: GK | C19: English | D19: Ashfaqulla Khan: Martyr Who Fought British Rule With Brotherhood | E19: 1 | F19: =vlookup(E19,Category_ID!A:B,2,0) -> Indian History | G19: 3 | H19: =vlookup(G19,Sub_Category_ID!A:C,3,0) -> Modern History | I19: 39 | J19: =vlookup(I19,Section!A:D,4,0) -> Freedom Fighters and Their Contributions | K19: a29c7b82effec14da37d2e93593aaf8e.jpg | M19: 1757073643_Ashfaqulla Khan.pdf | N19: Ashfaqulla Khan was a freedom fighter and poet who fought British colonialism through revolutionary means. As a key member of the Hindustan Republican Association, he took part in the Kakori Train Robbery. Committed to Hindu-Muslim unity and patriotic ideals, he was executed in 1927. His martyrdom stands as a symbol of secular nationalism and youthful sacrifice.\r\n | O19: 0000-00-00 00:00:00 | P19: 0000-00-00 00:00:00
A20: 91 | B20: GK | C20: English | D20: Thakur Roshan Singh: Forgotten Martyr of the Kakori Conspiracy Case | E20: 1 | F20: =vlookup(E20,Category_ID!A:B,2,0) -> Indian History | G20: 3 | H20: =vlookup(G20,Sub_Category_ID!A:C,3,0) -> Modern History | I20: 39 | J20: =vlookup(I20,Section!A:D,4,0) -> Freedom Fighters and Their Contributions | K20: b2ab35ab250a47fd14a94d9ef3981376.jpg | M20: 1757073855_Thakur Roshan Singh.pdf | N20: Thakur Roshan Singh was a revolutionary associated with the Hindustan Republican Association. Though not directly involved in the Kakori train robbery, he was arrested for earlier revolutionary actions and executed for conspiracy. He was hanged on 19 December 1927, alongside Ashfaqulla Khan and Ram Prasad Bismil, marking him as one of the silent martyrs of India’s freedom movement.\r\n | O20: 0000-00-00 00:00:00 | P20: 0000-00-00 00:00:00
... A23: 94 | B23: GK | C23: English | D23: Mangal Pandey Ignited 1857 Revolt, Defied British Colonial Oppression Boldly | E23: 1 | F23: =vlookup(E23,Category_ID!A:B,2,0) -> Indian History | G23: 3 | H23: =vlookup(G23,Sub_Category_ID!A:C,3,0) -> Modern History | I23: 39 | J23: =vlookup(I23,Section!A:D,4,0) -> Freedom Fighters and Their Contributions | K23: 26343e02ac546ffd4d9eccdb13300c8b.jpg | M23: 1757075121_Mangal Pandey.pdf | N23: Mangal Pandey, a sepoy in the 34th Bengal Native Infantry, ignited India’s First War of Independence in 1857 by revolting against the use of greased rifle cartridges that insulted Hindu and Muslim religious sentiments. His act of rebellion at Barrackpore led to his execution but became the symbolic starting point of India\'s armed struggle against British colonial rule.\r\n | O23: 0000-00-00 00:00:00 | P23: 0000-00-00 00:00:00
A24: 95 | B24: GK | C24: English | D24: sdcwnsdcn | F24: =vlookup(E24,Category_ID!A:B,2,0) -> #N/A | H24: =vlookup(G24,Sub_Category_ID!A:C,3,0) -> #N/A | I24: 1 | J24: =vlookup(I24,Section!A:D,4,0) -> #N/A | K24: 16a1bb5ce98eeba49f8152c14999fd79.png | L24: https://example.com/images/history.jpg | M24: 1757171713_Advance_Topic.pdf | N24: wsdvesvc | O24: 0000-00-00 00:00:00 | P24: 0000-00-00 00:00:00
A25: 96 | B25: GK | C25: English | D25: Udham Singh Avenged Jallianwala Bagh Massacre, Martyred in London | E25: 1 | F25: =vlookup(E25,Category_ID!A:B,2,0) -> Indian History | G25: 3 | H25: =vlookup(G25,Sub_Category_ID!A:C,3,0) -> Modern History | I25: 39 | J25: =vlookup(I25,Section!A:D,4,0) -> Freedom Fighters and Their Contributions | K25: 6e91ca4aeeec6f9a885bfe8885e514b6.jpg | M25: 1757323013_Udham Singh.pdf | N25: Udham Singh, a revolutionary from Punjab, assassinated General Michael O\'Dwyer in 1940 to avenge the 1919 Jallianwala Bagh massacre. A member of the Ghadar Party and later influenced by socialism, Singh waited over two decades for justice. Captured and tried in Britain, he was hanged in London. His sacrifice is remembered as a symbol of anti-colonial vengeance and resistance.\r\n | O25: 0000-00-00 00:00:00 | P25: 0000-00-00 00:00:00
A26: 97 | B26: GK | C26: English | D26: Teen Revolutionary Anant Kanhere Hanged for Killing British Collector Jackson | E26: 1 | F26: =vlookup(E26,Category_ID!A:B,2,0) -> Indian History | G26: 3 | H26: =vlookup(G26,Sub_Category_ID!A:C,3,0) -> Modern History | I26: 39 | J26: =vlookup(I26,Section!A:D,4,0) -> Freedom Fighters and Their Contributions | K26: 532922707e0ef6135c1f61eb069b026c.jpg | L26: https://example.com/images/history.jpg | M26: 1757323586_Anant Laxman Kanher.pdf | N26: Anant Laxman Kanher, a young revolutionary from Maharashtra, assassinated British Collector A.M.T. Jackson in 1909 to protest colonial oppression. Influenced by nationalist ideals, he carried out the act at a public event in Nashik. Arrested on the spot, he was tried and hanged at age 18 in 1910. His execution remains a symbol of youthful sacrifice in India’s freedom movement.\r\n | O26: 0000-00-00 00:00:00 | P26: 0000-00-00 00:00:00
A27: 98 | B27: GK | C27: English | D27: Teen Freedom Fighter Hemu Kalani Hanged by British at Nineteen | E27: 1 | F27: =vlookup(E27,Category_ID!A:B,2,0) -> Indian History | G27: 3 | H27: =vlookup(G27,Sub_Category_ID!A:C,3,0) -> Modern History | I27: 39 | J27: =vlookup(I27,Section!A:D,4,0) -> Freedom Fighters and Their Contributions | K27: e2a1e35472cb0c7621545c2533bd960f.jpg | M27: 1757323736_Hemu Kalani.pdf | N27: Hemu Kalani was a teenage revolutionary from Sindh who led anti-British protests during the Quit India Movement. He attempted to derail a British military train carrying troops and arms. Caught and tortured, Hemu refused to betray his comrades. He was hanged on January 21, 1943, becoming one of the youngest martyrs of India’s struggle for independence.\r\n | O27: 0000-00-00 00:00:00 | P27: 0000-00-00 00:00:00
A28: 99 | B28: GK | C28: English | D28: Satyendranath Bosu Hanged For Role In Chittagong Armoury Raid | E28: 1 | F28: =vlookup(E28,Category_ID!A:B,2,0) -> Indian History | G28: 3 | H28: =vlookup(G28,Sub_Category_ID!A:C,3,0) -> Modern History | I28: 39 | J28: =vlookup(I28,Section!A:D,4,0) -> Freedom Fighters and Their Contributions | K28: 503e30b9542bd1b84eef19f9f5606835.jpg | M28: 1757324132_Satyendranath Bosu .pdf | N28: Satyendranath Bosu was a Bengali revolutionary associated with the Chittagong Armoury Raid of 1930 led by Surya Sen. Deeply inspired by nationalist ideas, he played a key role in the armed insurrection against British rule. Captured after the raid, he was sentenced to death and hanged in July 1934, becoming one of the unsung heroes of India’s independence movement.\r\n | O28: 0000-00-00 00:00:00 | P28: 0000-00-00 00:00:00
A29: 100 | B29: GK | C29: English | D29: Ramkrishna Biswas Hanged for Attempted Assassination of British Officer | E29: 1 | F29: =vlookup(E29,Category_ID!A:B,2,0) -> Indian History | G29: 3 | H29: =vlookup(G29,Sub_Category_ID!A:C,3,0) -> Modern History | I29: 39 | J29: =vlookup(I29,Section!A:D,4,0) -> Freedom Fighters and Their Contributions | K29: c43344f70928ccd15603430f1f37fa86.jpg | M29: 1757324701_Ramkrishna Biswas .pdf | N29: Ramkrishna Biswas was a revolutionary from Bengal associated with the Jugantar group. In 1930, he attempted to assassinate a British magistrate as an act of anti-colonial resistance but mistakenly killed another officer. He was arrested, tried, and hanged in 1931. His execution inspired numerous revolutionaries, including Subhas Chandra Bose, and remains a symbol of youthful sacrifice.\r\n | O29: 0000-00-00 00:00:00 | P29: 0000-00-00 00:00:00
A30: 101 | B30: GK | C30: English | D30: Ghulam Husain Martyred For Role In Chittagong Armoury Raid, 1934 | E30: 1 | F30: =vlookup(E30,Category_ID!A:B,2,0) -> Indian History | G30: 3 | H30: =vlookup(G30,Sub_Category_ID!A:C,3,0) -> Modern History | I30: 39 | J30: =vlookup(I30,Section!A:D,4,0) -> Freedom Fighters and Their Contributions | K30: 94a696c0c056c066d6b6b29f03f5724c.jpg | M30: 1757325085_Ghulam Husain .pdf | N30: Ghulam Husain, a brave revolutionary from Bengal, participated in the Chittagong Armoury Raid of 1930, orchestrated by Surya Sen. His mission was to liberate India through armed rebellion. Arrested during the British crackdown, he was sentenced to death and hanged in July 1934. Though less known, he remains an important figure in India\'s armed freedom struggle.\r\n | O30: 0000-00-00 00:00:00 | P30: 0000-00-00 00:00:00
A31: 102 | B31: GK | C31: English | D31: Basanta Kumar Biswas: Young Revolutionary Hanged for Delhi Bomb Attack | E31: 1 | F31: =vlookup(E31,Category_ID!A:B,2,0) -> Indian History | G31: 3 | H31: =vlookup(G31,Sub_Category_ID!A:C,3,0) -> Modern History | I31: 39 | J31: =vlookup(I31,Section!A:D,4,0) -> Freedom Fighters and Their Contributions | K31: f28eb9a77995657b79378d1e2d2fcdaa.jpg | M31: 1757325978_Basanta Kumar Biswas.pdf | N31: Basanta Kumar Biswas, a young Bengali revolutionary, played a key role in the 1912 Delhi Conspiracy. At just 18, he was involved in an assassination attempt on Viceroy Lord Hardinge during a state procession. Arrested and tried under the British regime, he was hanged on 11 May 1915. His sacrifice remains a powerful symbol of youthful patriotism.\r\n | O31: 0000-00-00 00:00:00 | P31: 0000-00-00 00:00:00
A32: 103 | B32: GK | C32: English | D32: Bhai Balmukund: Delhi Conspiracy Martyr Executed in British India | E32: 1 | F32: =vlookup(E32,Category_ID!A:B,2,0) -> Indian History | G32: 3 | H32: =vlookup(G32,Sub_Category_ID!A:C,3,0) -> Modern History | I32: 39 | J32: =vlookup(I32,Section!A:D,4,0) -> Freedom Fighters and Their Contributions | K32: 12a2d9019baf49f29d2ea5285ecd6b93.jpg | M32: 1757326643_Bhai Balmukund.pdf | N32: Bhai Balmukund was a revolutionary deeply involved in the 1912 Delhi Conspiracy, which targeted Viceroy Lord Hardinge. A cousin of revolutionary Bhai Parmanand, Balmukund was arrested in 1914, tried under charges of conspiracy and sedition, and hanged at the Lahore Central Jail in May 1915. He remains remembered as a brave nationalist who sacrificed his life at just 26.\r\n | O32: 0000-00-00 00:00:00 | P32: 0000-00-00 00:00:00
A33: 104 | B33: GK | C33: English | D33: Tatya Tope Led Fierce Guerrilla Campaigns During 1857 Revolt Heroically | E33: 1 | F33: =vlookup(E33,Category_ID!A:B,2,0) -> Indian History | G33: 3 | H33: =vlookup(G33,Sub_Category_ID!A:C,3,0) -> Modern History | I33: 39 | J33: =vlookup(I33,Section!A:D,4,0) -> Freedom Fighters and Their Contributions | K33: fc00efc148feda71e54ddfb9e3aacd6d.jpg | M33: 1757320745_Tatya Tope.pdf | N33: Tatya Tope, a key leader in the 1857 Revolt, was a trusted general of Nana Sahib. Known for his strategic brilliance and guerrilla warfare, he led forces in Kanpur, Gwalior, and central India. Even after losing territory, he continued resistance until captured and executed in 1859. Tatya remains one of India’s earliest revolutionary icons for his unmatched military defiance. | O33: 0000-00-00 00:00:00 | P33: 0000-00-00 00:00:00
A34: 105 | B34: GK | C34: English | D34: Vanchinathan Assassinated British Collector, Sparked Early Nationalist Resistance | E34: 1 | F34: =vlookup(E34,Category_ID!A:B,2,0) -> Indian History | G34: 3 | H34: =vlookup(G34,Sub_Category_ID!A:C,3,0) -> Modern History | I34: 39 | J34: =vlookup(I34,Section!A:D,4,0) -> Freedom Fighters and Their Contributions | K34: f4636d46aa34840f203aef4ab59d4c1c.jpg | M34: 1757321161_Vanchinathan Iyer.pdf | N34: Vanchinathan was a Tamil revolutionary who assassinated British Collector Robert Ashe in 1911 at Maniyachi railway station. Motivated by the Swadeshi movement and colonial atrocities, he viewed Ashe as an oppressor. After the act, Vanchinathan died by suicide to avoid capture. Though controversial, he remains a symbol of early militant resistance in India’s freedom struggle, especially in South India.\r\n | O34: 0000-00-00 00:00:00 | P34: 0000-00-00 00:00:00
A35: 106 | B35: GK | C35: English | D35: Dinesh Gupta Fought Colonial Rule, Embraced Martyrdom With Courage | E35: 1 | F35: =vlookup(E35,Category_ID!A:B,2,0) -> Indian History | G35: 3 | H35: =vlookup(G35,Sub_Category_ID!A:C,3,0) -> Modern History | I35: 39 | J35: =vlookup(I35,Section!A:D,4,0) -> Freedom Fighters and Their Contributions | K35: 55a54b3b9621cb2f74952b38edc437b2.jpg | M35: 1757321583_Dinesh Gupta.pdf | N35: Dinesh Gupta, a young Bengali revolutionary, was a key figure in India’s anti-colonial movement. In 1931, he and his comrades attacked the Writers’ Building in Kolkata to assassinate British officials. Though the mission partly failed, Gupta was captured and executed at just 19. His bravery and sacrifice remain etched in the history of Bengal’s revolutionary struggle against British rule.\r\n | O35: 0000-00-00 00:00:00 | P35: 0000-00-00 00:00:00
A36: 107 | B36: GK | C36: English | D36: Kartar Singh Sarabha Inspired Ghadar Movement, Martyred at Age Nineteen | E36: 1 | F36: =vlookup(E36,Category_ID!A:B,2,0) -> Indian History | G36: 3 | H36: =vlookup(G36,Sub_Category_ID!A:C,3,0) -> Modern History | I36: 39 | J36: =vlookup(I36,Section!A:D,4,0) -> Freedom Fighters and Their Contributions | K36: 69082f39abe02ae66e8fde17be2231ab.jpg | M36: 1757322239_Kartar Singh Sarabha.pdf | N36: Kartar Singh Sarabha was a fiery revolutionary and one of the youngest martyrs of India’s freedom struggle. A leader of the Ghadar Movement, he sought to incite mutiny in the British Indian Army during World War I. Caught by the British, he was tried and hanged at the age of 19. His sacrifice deeply inspired revolutionaries like Bhagat Singh. | O36: 0000-00-00 00:00:00 | P36: 0000-00-00 00:00:00
A37: 108 | B37: GK | C37: English | D37: Pandit Kanshi Ram: Ghadar Revolutionary Martyred for India’s Freedom Struggle | E37: 1 | F37: =vlookup(E37,Category_ID!A:B,2,0) -> Indian History | G37: 3 | H37: =vlookup(G37,Sub_Category_ID!A:C,3,0) -> Modern History | I37: 39 | J37: =vlookup(I37,Section!A:D,4,0) -> Freedom Fighters and Their Contributions | K37: fa260a13552ab5757cc6cbf54d388f2d.jpg | M37: 1757327281_Pandit Kanshi Ram.pdf | N37: Pandit Kanshi Ram was a key leader in the Ghadar Movement, which aimed to incite armed revolt against British rule in India. A close associate of Lala Hardayal and Vishnu Ganesh Pingle, he was arrested for attempting mutiny in the British Indian Army. He was tried under the Lahore Conspiracy Case and hanged in Lahore on 27 March 1915.\r\n | O37: 0000-00-00 00:00:00 | P37: 0000-00-00 00:00:00
A38: 109 | B38: GK | C38: English | D38: Babarao Savarkar: Revolutionary Who Faced Kala Pani Punishment Bravely | E38: 1 | F38: =vlookup(E38,Category_ID!A:B,2,0) -> Indian History | G38: 3 | H38: =vlookup(G38,Sub_Category_ID!A:C,3,0) -> Modern History | I38: 39 | J38: =vlookup(I38,Section!A:D,4,0) -> Freedom Fighters and Their Contributions | K38: 9e21d0144e3631ba58175ea10afcc638.jpg | M38: 1757328080_Babarao Savarkar.pdf | N38: Babarao Savarkar, elder brother of Veer Savarkar, was a fearless revolutionary and co-founder of the Abhinav Bharat Society. Convicted for sedition, he was sentenced to Kala Pani at Cellular Jail, Andaman. Despite harsh conditions, he remained committed to India’s independence. A forgotten patriot, his life embodies the unsung sacrifices made in India’s freedom movement.\r\n | O38: 0000-00-00 00:00:00 | P38: 0000-00-00 00:00:00
... A60: 131 | B60: GK | C60: English | D60: India’s Parliament: Structure, Lawmaking, Committees, and Privileges Explained | E60: 5 | F60: =vlookup(E60,Category_ID!A:B,2,0) -> Polity and Governance | G60: 28 | H60: =vlookup(G60,Sub_Category_ID!A:C,3,0) -> Indian Constitution | I60: 59 | J60: =vlookup(I60,Section!A:D,4,0) -> Union Government | K60: 8f6babc8a0524edccbc1182659d650f6.jpg | M60: 1757412737_India’s Parliament_ Structure, Lawmaking, Committees, and Privileges Explained.pdf | N60: India’s Parliament, comprising the President, Lok Sabha, and Rajya Sabha, is central to governance. It frames laws through a structured legislative process, aided by specialized committees. Parliamentary privileges safeguard members’ independence but face criticism for misuse and ambiguity. Key judicial rulings and reforms aim to balance these privileges with transparency, accountability, and the democratic spirit.\r\n | O60: 0000-00-00 00:00:00 | P60: 0000-00-00 00:00:00
A61: 132 | B61: GK | C61: English | D61: Judiciary in India: Balancing Activism, Restraint, and Constitutional Mandates | E61: 5 | F61: =vlookup(E61,Category_ID!A:B,2,0) -> Polity and Governance | G61: 28 | H61: =vlookup(G61,Sub_Category_ID!A:C,3,0) -> Indian Constitution | I61: 59 | J61: =vlookup(I61,Section!A:D,4,0) -> Union Government | K61: be1cac4a648d4af9bb2741af4b4254e2.png | M61: 1757413505_Judiciary in India_ Balancing Activism, Restraint, and Constitutional Mandates.pdf | N61: The Indian judiciary plays a pivotal role in safeguarding constitutional rights through judicial review, activism, and restraint. While activism advances rights and fills legislative gaps, overreach risks undermining separation of powers. Landmark cases like Kesavananda Bharati, Maneka Gandhi, and Vishaka shaped public law, highlighting the judiciary’s role in democracy, yet emphasizing the need for principled limits.\r\n | O61: 0000-00-00 00:00:00 | P61: 45934.569
A62: 133 | B62: GK | C62: English | D62: Constitutional Role, Powers, and Challenges of India’s State Governors | E62: 5 | F62: =vlookup(E62,Category_ID!A:B,2,0) -> Polity and Governance | G62: 28 | H62: =vlookup(G62,Sub_Category_ID!A:C,3,0) -> Indian Constitution | I62: 60 | J62: =vlookup(I62,Section!A:D,4,0) -> State Government | K62: 8c9186b25f7ecea9603e9ce1c3223c58.jpg | M62: 1757413747_Constitutional Role, Powers, and Challenges of India’s State Governors.pdf | N62: The Governor, India’s constitutional head of state, bridges the Centre and State. Appointed by the President, the role carries executive, legislative, and judicial powers, balanced by constitutional conventions and judicial rulings. While intended as a neutral office, controversies over political bias, misuse of Article 356, and delayed bill assent persist, prompting calls for reforms and stricter accountability.\r\n | O62: 0000-00-00 00:00:00 | P62: 0000-00-00 00:00:00
A63: 134 | B63: GK | C63: English | D63: Chief Minister and Council: Pillars of India’s State Governance | E63: 5 | F63: =vlookup(E63,Category_ID!A:B,2,0) -> Polity and Governance | G63: 28 | H63: =vlookup(G63,Sub_Category_ID!A:C,3,0) -> Indian Constitution | I63: 60 | J63: =vlookup(I63,Section!A:D,4,0) -> State Government | K63: a681913d0730d53e33d06740e29c732c.png | M63: 1757415167_Chief Minister and Council_ Pillars of India’s State Governance.pdf | N63: The Chief Minister and Council of Ministers form the real executive at the state level, guiding policy, legislation, and administration within India’s federal framework. Appointed by the Governor, they operate under collective and individual responsibility to the Legislative Assembly. Bound by constitutional provisions, they ensure governance continuity, uphold democratic principles, and act as the state’s decision-making core.\r\n | O63: 0000-00-00 00:00:00 | P63: 0000-00-00 00:00:00
A64: 135 | B64: GK | C64: English | D64: Bicameral State Legislatures: Structure, Powers, and Role in India | E64: 5 | F64: =vlookup(E64,Category_ID!A:B,2,0) -> Polity and Governance | G64: 28 | H64: =vlookup(G64,Sub_Category_ID!A:C,3,0) -> Indian Constitution | I64: 60 | J64: =vlookup(I64,Section!A:D,4,0) -> State Government | K64: 9bdeaedf4cd834af8f6a2016de95351a.jpg | M64: 1757415318_Bicameral State Legislatures_ Structure, Powers, and Role in India.pdf | N64: India’s federal system grants states legislative bodies that may be unicameral or bicameral. Six states have Legislative Councils alongside Assemblies, serving as review chambers. Governed by Articles 169, 171, and 172, these councils scrutinize laws, represent experts, and maintain political continuity, though with limited powers compared to assemblies. Their creation or abolition requires Parliament’s approval after state resolution.\r\n | O64: 0000-00-00 00:00:00 | P64: 0000-00-00 00:00:00
A65: 136 | B65: GK | C65: English | D65: High and Subordinate Courts: Structure, Powers, and Constitutional Role | E65: 5 | F65: =vlookup(E65,Category_ID!A:B,2,0) -> Polity and Governance | G65: 28 | H65: =vlookup(G65,Sub_Category_ID!A:C,3,0) -> Indian Constitution | I65: 60 | J65: =vlookup(I65,Section!A:D,4,0) -> State Government | K65: 4c4d9a0a2c08757495c9399853649883.png | M65: 1757416514_High and Subordinate Courts_ Structure, Powers, and Constitutional Role.pdf | N65: India’s judicial system follows a single, integrated hierarchy with High Courts as the top authority in states and Subordinate Courts as the grassroots level of justice. High Courts ensure constitutional compliance, fundamental rights protection, and appellate review, while Subordinate Courts handle day-to-day civil, criminal, and revenue disputes. Both face challenges like backlog, vacancies, and infrastructure gaps.\r\n | O65: 0000-00-00 00:00:00 | P65: 0000-00-00 00:00:00
A66: 137 | B66: GK | C66: English | D66: 73rd Amendment: Strengthening Panchayati Raj for Grassroots Democracy in India | E66: 5 | F66: =vlookup(E66,Category_ID!A:B,2,0) -> Polity and Governance | G66: 28 | H66: =vlookup(G66,Sub_Category_ID!A:C,3,0) -> Indian Constitution | I66: 61 | J66: =vlookup(I66,Section!A:D,4,0) -> Local Government | K66: 3eb77de8f5773f812294bfd29b991cd5.jpeg | M66: 1757418169_73rd Amendment_ Strengthening Panchayati Raj for Grassroots Democracy in India.pdf | N66: The 73rd Constitutional Amendment Act, 1992 institutionalized Panchayati Raj, ensuring democratic decentralization in rural India through a three-tier system, Gram Sabhas, reservations, and State Election/Finance Commissions. Covering 29 subjects in the 11th Schedule, it empowered local bodies but faces challenges like uneven devolution, fiscal dependence, and limited capacity. Strengthening PRIs is vital for inclusive, participatory rural governance.\r\n | O66: 0000-00-00 00:00:00 | P66: 0000-00-00 00:00:00
A67: 138 | B67: GK | C67: English | D67: Empowering Cities: The 74th Constitutional Amendment Reshapes Urban Governance | E67: 5 | F67: =vlookup(E67,Category_ID!A:B,2,0) -> Polity and Governance | G67: 28 | H67: =vlookup(G67,Sub_Category_ID!A:C,3,0) -> Indian Constitution | I67: 61 | J67: =vlookup(I67,Section!A:D,4,0) -> Local Government | K67: 614931fc42822551dbcc48888e788926.jpg | M67: 1757418320_Empowering Cities_ The 74th Constitutional Amendment Reshapes Urban Governance.pdf | N67: The 74th Constitutional Amendment Act, 1992 granted constitutional status to municipalities, institutionalizing urban local governance in India. By adding Part IX-A and the Twelfth Schedule, it defined structures, powers, functions, and finances of Urban Local Bodies. It sought to strengthen grassroots democracy, enhance citizen participation, and improve urban administration, though implementation has varied significantly across states.\r\n | O67: 0000-00-00 00:00:00 | P67: 0000-00-00 00:00:00
A68: 139 | B68: GK | C68: English | D68: Strengthening Local Governance: Challenges, Reforms, and Pathways to Empowerment | E68: 5 | F68: =vlookup(E68,Category_ID!A:B,2,0) -> Polity and Governance | G68: 28 | H68: =vlookup(G68,Sub_Category_ID!A:C,3,0) -> Indian Constitution | I68: 61 | J68: =vlookup(I68,Section!A:D,4,0) -> Local Government | K68: ea0c7928ed679fb0dbd532097cb1a75f.jpg | M68: 1757494295_Strengthening Local Governance_ Challenges, Reforms, and Pathways to Empowerment.pdf | N68: Local governance in India faces significant challenges, including inadequate fiscal autonomy, capacity gaps, political interference, and poor citizen participation. Despite constitutional provisions, many state governments delay decentralization, limiting the efficiency of urban and rural bodies. Strengthening legal frameworks, enhancing financial independence, building institutional capacity, and integrating technology are vital to ensure transparent, inclusive, and sustainable local governance.\r\n | O68: 0000-00-00 00:00:00 | P68: 0000-00-00 00:00:00
A69: 140 | B69: GK | C69: English | D69: Union Territories: Constitutional framework, governance challenges, reforms and current issues | E69: 5 | F69: =vlookup(E69,Category_ID!A:B,2,0) -> Polity and Governance | G69: 28 | H69: =vlookup(G69,Sub_Category_ID!A:C,3,0) -> Indian Constitution | I69: 62 | J69: =vlookup(I69,Section!A:D,4,0) -> Union Territories & Special Areas | K69: 6b4db510f858b6c648c356b95fb3c555.jpg | M69: 1757494462_Union Territories_ Constitutional framework, governance challenges, reforms and current issues.pdf | N69: Union Territories (UTs) are centrally administered units under Articles 239–241, each headed by an Administrator or Lieutenant Governor. Some UTs—Delhi, Puducherry, Jammu & Kashmir—have legislatures with limited powers, while others are directly governed by the Centre. Despite their strategic roles, UTs face democratic deficits, frequent Centre–local disputes, and structural fragility, prompting calls for reforms in governance, autonomy, and representation.\r\n | O69: 0000-00-00 00:00:00 | P69: 0000-00-00 00:00:00
A70: 141 | B70: GK | C70: English | D70: Fifth and Sixth Schedules: Constitutional Safeguards for India’s Tribal Areas | E70: 5 | F70: =vlookup(E70,Category_ID!A:B,2,0) -> Polity and Governance | G70: 28 | H70: =vlookup(G70,Sub_Category_ID!A:C,3,0) -> Indian Constitution | I70: 62 | J70: =vlookup(I70,Section!A:D,4,0) -> Union Territories & Special Areas | K70: 489174e5d11029d6ea2c10d5b7542437.jpg | M70: 1757494592_Fifth and Sixth Schedules_ Constitutional Safeguards for India’s Tribal Areas.pdf | N70: India’s Constitution safeguards tribal regions through the Fifth and Sixth Schedules. The Fifth Schedule governs Scheduled Areas in ten states via Governor’s regulations, Tribes Advisory Councils, and PESA powers for Gram Sabhas. The Sixth Schedule creates Autonomous Councils in select Northeastern states with legislative, executive, judicial, and fiscal authority. Both aim to protect tribal land, culture, and self-governance amid evolving challenges.\r\n | O70: 0000-00-00 00:00:00 | P70: 0000-00-00 00:00:00
A71: 142 | B71: GK | C71: English | D71: Election Commission & State Commissions: Constitutional Role, Structure, Powers, Reforms | E71: 5 | F71: =vlookup(E71,Category_ID!A:B,2,0) -> Polity and Governance | G71: 28 | H71: =vlookup(G71,Sub_Category_ID!A:C,3,0) -> Indian Constitution | I71: 63 | J71: =vlookup(I71,Section!A:D,4,0) -> Constitutional Bodies | K71: d411587e71e00a990eead4e84201133f.jpg | M71: 1757494795_Election Commission & State Commissions_ Constitutional Role, Structure, Powers, Reforms.pdf | N71: The Election Commission of India (ECI) under Article 324 oversees parliamentary, state legislature, and presidential elections, while State Election Commissions (SECs) under Articles 243K and 243ZA conduct local body polls. This article explains their constitutional basis, powers, composition, appointment reforms, case laws, and independence safeguards, along with challenges like appointment controversies, transparency debates, and delays in local elections.Election Commission of India (ECI) was established on 25 January 1950.State Election Commissions (SECs) were established in 1993\r\n | O71: 0000-00-00 00:00:00 | P71: 0000-00-00 00:00:00
A72: 143 | B72: GK | C72: English | D72: UPSC and State PSCs: Structure, Powers, Functions, Constitutional Safeguards | E72: 5 | F72: =vlookup(E72,Category_ID!A:B,2,0) -> Polity and Governance | G72: 28 | H72: =vlookup(G72,Sub_Category_ID!A:C,3,0) -> Indian Constitution | I72: 63 | J72: =vlookup(I72,Section!A:D,4,0) -> Constitutional Bodies | K72: 866a07e3e49c8ba9d2901749dd24b8e0.jpeg | M72: 1757494927_Election Commission & State Commissions_ Constitutional Role, Structure, Powers, Reforms.pdf | N72: The Union Public Service Commission (UPSC) and State Public Service Commissions (SPSCs) are independent constitutional bodies established under Articles 315–323 of Part XIV. UPSC recruits for Union and All-India Services, while SPSC recruits for State services. With secure tenure, removal safeguards, financial autonomy, and defined consultative roles, they ensure merit-based recruitment, uphold administrative integrity, and maintain transparent selection processes across government services.\r\n | O72: 0000-00-00 00:00:00 | P72: 0000-00-00 00:00:00
A73: 144 | B73: GK | C73: English | E73: 5 | F73: =vlookup(E73,Category_ID!A:B,2,0) -> Polity and Governance | G73: 28 | H73: =vlookup(G73,Sub_Category_ID!A:C,3,0) -> Indian Constitution | I73: 63 | J73: =vlookup(I73,Section!A:D,4,0) -> Constitutional Bodies | K73: 8d6d4c64a954ac856cb6540a08e75204.jpg | M73: 1759570047_PUblished - Finance Commission_ Fiscal federalism, devolution, challenges, and future directions.pdf | N73: The Finance Commission, a constitutional body under Article 280, defines Union–State fiscal relations every five years. It recommends tax devolution, grants-in-aid, and resource allocation principles. While its role is central to cooperative federalism, challenges remain—data gaps, political economy pressures, and implementation delays. The 16th Commission, chaired by Arvind Panagariya. \r\n | O73: 0000-00-00 00:00:00 | P73: 45934.623
A74: 145 | B74: GK | C74: English | D74: Comptroller and Auditor General: Guardian of India’s Public Financial Accountability | E74: 5 | F74: =vlookup(E74,Category_ID!A:B,2,0) -> Polity and Governance | G74: 28 | H74: =vlookup(G74,Sub_Category_ID!A:C,3,0) -> Indian Constitution | I74: 63 | J74: =vlookup(I74,Section!A:D,4,0) -> Constitutional Bodies | K74: bdc0646910c7ae31fe9709534583f931.jpg | M74: 1757495312_Comptroller and Auditor General_ Guardian of India’s Public Financial Accountability.pdf | N74: The Comptroller and Auditor General (CAG) of India, established under Article 148,which came into effect on 26 January 1950. audits all receipts, expenditure, and accounts of the Union and States. Appointed by the President for six years or until 65 years, the CAG ensures transparency, accountability, and fiscal discipline. Its reports influence parliamentary oversight and strengthen India’s democratic governance by monitoring financial integrity.\r\n | O74: 0000-00-00 00:00:00 | P74: 0000-00-00 00:00:00
A75: 146 | B75: GK | C75: English | D75: Guardians of justice: NCSC, NCST and NCBC in action | E75: 5 | F75: =vlookup(E75,Category_ID!A:B,2,0) -> Polity and Governance | G75: 28 | H75: =vlookup(G75,Sub_Category_ID!A:C,3,0) -> Indian Constitution | I75: 63 | J75: =vlookup(I75,Section!A:D,4,0) -> Constitutional Bodies | K75: f8a2d7516ea3d9ca5b0b2345c12498b0.jpg | M75: 1757495495_Guardians of justice_ NCSC, NCST and NCBC in action.pdf | N75: The National Commission for Scheduled Castes (Art. 338), Scheduled Tribes (Art. 338A) and Backward Classes (Art. 338B) safeguard constitutional rights of vulnerable communities. They investigate complaints, monitor legal safeguards, advise governments, and report to the President. Originating from constitutional amendments, these bodies now face capacity and coordination challenges but remain vital to social justice in India.\r\n | O75: 0000-00-00 00:00:00 | P75: 0000-00-00 00:00:00
A76: 147 | B76: GK | C76: English | D76: NITI Aayog: Driving India’s Inclusive Growth through Cooperative Federalism | E76: 5 | F76: =vlookup(E76,Category_ID!A:B,2,0) -> Polity and Governance | G76: 28 | H76: =vlookup(G76,Sub_Category_ID!A:C,3,0) -> Indian Constitution | I76: 64 | J76: =vlookup(I76,Section!A:D,4,0) -> Non Constitutional Bodies | K76: f60e75aba6a51bcd98e1de21df49126a.jpg | M76: 1757495785_NITI Aayog_ Driving India’s Inclusive Growth through Cooperative Federalism.pdf | N76: Established on January 1, 2015, NITI Aayog replaced the Planning Commission as India’s apex public policy think tank. Led by the Prime Minister, it fosters cooperative and competitive federalism, drives innovation, monitors SDGs, and implements transformative initiatives like the Aspirational Districts and Blocks Programmes. Through strategic vision, data-driven governance, and state engagement, it aims to achieve Viksit Bharat @2047.\r\n | O76: 0000-00-00 00:00:00 | P76: 0000-00-00 00:00:00
A77: 148 | B77: GK | C77: English | D77: NHRC, SHRCs & Coordinated Commissions: Mandate, Limitations, Strengthening Institutional Synergy | E77: 5 | F77: =vlookup(E77,Category_ID!A:B,2,0) -> Polity and Governance | G77: 28 | H77: =vlookup(G77,Sub_Category_ID!A:C,3,0) -> Indian Constitution | I77: 64 | J77: =vlookup(I77,Section!A:D,4,0) -> Non Constitutional Bodies | K77: 4f355aae0ae0b2868e69f3056aa9fda7.jpg | M77: 1757498287_NHRC, SHRCs & Coordinated Commissions_ Mandate, Limitations, Strengthening Institutional Synergy.pdf | N77: The NHRC (1993, amended 2006 & 2019) and SHRCs safeguard constitutional rights—life, liberty, equality, and dignity. They can investigate violations with civil-court powers, visit institutions, and recommend reliefs. Constraints include time-bar, non-binding orders, and limited armed-forces jurisdiction. The NHRC now collaborates with seven national commissions to streamline policy, research, and enforcement. Reforms focus on greater independence, proactive mandates, resources, legal powers, and public outreach.\r\n | O77: 0000-00-00 00:00:00 | P77: 0000-00-00 00:00:00
A78: 149 | B78: GK | C78: English | D78: Central Vigilance Commission: India’s independent statutory anti-corruption oversight body | E78: 5 | F78: =vlookup(E78,Category_ID!A:B,2,0) -> Polity and Governance | G78: 28 | H78: =vlookup(G78,Sub_Category_ID!A:C,3,0) -> Indian Constitution | I78: 64 | J78: =vlookup(I78,Section!A:D,4,0) -> Non Constitutional Bodies | K78: 017599d26f128238b38b44afb5bc7f50.png | M78: 1757498748_Central Vigilance Commission_ India’s independent statutory anti-corruption oversight body.pdf | N78: The Central Vigilance Commission (CVC), established in 1964 on Santhanam Committee’s recommendation and granted statutory status by the CVC Act, 2003, is India’s apex vigilance body. It supervises vigilance administration in Union Government organisations, oversees CBI investigations under the Prevention of Corruption Act, advises on disciplinary actions, monitors procurement integrity, and safeguards whistleblowers. Independent of executive control, it reports directly to Parliament.\r\n | O78: 0000-00-00 00:00:00 | P78: 0000-00-00 00:00:00
A79: 150 | B79: GK | C79: English | D79: India’s Lokpal & Lokayuktas: Statutory Anti-Corruption Watchdogs Ensuring Accountability | E79: 5 | F79: =vlookup(E79,Category_ID!A:B,2,0) -> Polity and Governance | G79: 28 | H79: =vlookup(G79,Sub_Category_ID!A:C,3,0) -> Indian Constitution | I79: 64 | J79: =vlookup(I79,Section!A:D,4,0) -> Non Constitutional Bodies | K79: 4e80a90eebe8aaf0b7f1fa883e3f4718.jpg | M79: 1757498845_India’s Lokpal & Lokayuktas_ Statutory Anti-Corruption Watchdogs Ensuring Accountability.pdf | N79: The Lokpal and Lokayuktas Act, 2013 mandates statutory ombudsmen at both Union (Lokpal) and State (Lokayukta) levels to investigate corruption by public functionaries. Enacted on 1 January and effective from 16 January 2014, Lokpal’s jurisdiction spans the Prime Minister (with narrow exceptions), Ministers, MPs, and all Group A–D officials. States must similarly establish Lokayuktas under their own laws. \r\n | O79: 0000-00-00 00:00:00 | P79: 0000-00-00 00:00:00
A80: 151 | B80: GK | C80: English | D80: National Emergency in India: Constitutional grounds, procedure, effects, safeguards | E80: 5 | F80: =vlookup(E80,Category_ID!A:B,2,0) -> Polity and Governance | G80: 28 | H80: =vlookup(G80,Sub_Category_ID!A:C,3,0) -> Indian Constitution | I80: 65 | J80: =vlookup(I80,Section!A:D,4,0) -> Emergency Provisions | K80: abacabd26adacd63b6bdf4bc3d58c516.jpeg | M80: 1757498956_National Emergency in India_ Constitutional grounds, procedure, effects, safeguards.pdf | N80: A National Emergency (Article 352) may be proclaimed by the President when India’s security is threatened by war, external aggression, or armed rebellion. The 44th Amendment introduced safeguards—written Cabinet advice, special majority within one month, six-month renewals, and Lok Sabha disapproval power. It alters Centre–State powers, affects Fundamental Rights (Arts. 358–359), and has been declared thrice: 1962, 1971, and 1975.\r\n | O80: 0000-00-00 00:00:00 | P80: 0000-00-00 00:00:00
A81: 152 | B81: GK | C81: English | D81: State Emergency: Article 356 and President’s Rule in India | E81: 5 | F81: =vlookup(E81,Category_ID!A:B,2,0) -> Polity and Governance | G81: 28 | H81: =vlookup(G81,Sub_Category_ID!A:C,3,0) -> Indian Constitution | I81: 65 | J81: =vlookup(I81,Section!A:D,4,0) -> Emergency Provisions | K81: ff384a20b3a167581515c55d23bccdf8.jpg | M81: 1757499887_State Emergency_ Article 356 and President’s Rule in India.pdf | N81: Article 356 empowers the President to impose President’s Rule in a state if its constitutional machinery fails. It suspends the state government and transfers legislative and executive powers to the Centre. Although intended as a safeguard, its misuse for political purposes has drawn criticism. Judicial review and constitutional amendments now regulate its imposition.\r\n | O81: 0000-00-00 00:00:00 | P81: 0000-00-00 00:00:00
A82: 153 | B82: GK | C82: English | D82: Financial Emergency: Powers, Procedure, Effects, Safeguards under Article 360 | E82: 5 | F82: =vlookup(E82,Category_ID!A:B,2,0) -> Polity and Governance | G82: 28 | H82: =vlookup(G82,Sub_Category_ID!A:C,3,0) -> Indian Constitution | I82: 65 | J82: =vlookup(I82,Section!A:D,4,0) -> Emergency Provisions | K82: 1927c60a95e23c57ffecbb7de9d80a6c.jpg | M82: 1757500081_Financial Emergency_ Powers, Procedure, Effects, Safeguards under Article 360.pdf | N82: Article 360 empowers the President to proclaim a Financial Emergency if India’s financial stability or credit is threatened. Parliament must approve it within two months. It authorises Union directions to States, salary cuts (including judges), and reservation of State Money Bills for Presidential consideration. No such emergency has ever been declared. The 44th Amendment restored judicial review over the proclamation.\r\n | O82: 0000-00-00 00:00:00 | P82: 0000-00-00 00:00:00
A83: 154 | B83: GK | C83: English | D83: Centre–State Legislative Relations: Constitutional framework, powers, and conflict resolution | E83: 5 | F83: =vlookup(E83,Category_ID!A:B,2,0) -> Polity and Governance | G83: 28 | H83: =vlookup(G83,Sub_Category_ID!A:C,3,0) -> Indian Constitution | I83: 66 | J83: =vlookup(I83,Section!A:D,4,0) -> Centre-State Relations | K83: be92be7ad7839feaadb8f48c33546c33.jpg | M83: 1757500314_Centre–State Legislative Relations_ Constitutional framework, powers, and conflict resolution.pdf | N83: Legislative relations in India, governed by Part XI (Articles 245–255) and the Seventh Schedule, define the law-making powers of Parliament and State Legislatures. The Constitution outlines territorial extent, distribution of subjects, special circumstances for Parliament’s intervention in the State List, and Centre’s control over State laws. Federal balance is maintained through doctrines, emergency provisions, and constitutional safeguards.\r\n | O83: 0000-00-00 00:00:00 | P83: 0000-00-00 00:00:00
A84: 155 | B84: GK | C84: English | D84: Centre–State Administrative Relations: Powers, Duties, Coordination, and Emergency Controls | E84: 5 | F84: =vlookup(E84,Category_ID!A:B,2,0) -> Polity and Governance | G84: 28 | H84: =vlookup(G84,Sub_Category_ID!A:C,3,0) -> Indian Constitution | I84: 66 | J84: =vlookup(I84,Section!A:D,4,0) -> Centre-State Relations | K84: 81942bb81c1bb16ccf3fb23aa4aaa581.jpg | M84: 1757500905_Centre–State Administrative Relations_ Powers, Duties, Coordination, and Emergency Controls.pdf | N84: Administrative Relations under the Indian Constitution govern the distribution and coordination of executive powers between the Union and States. Rooted in Articles 73, 162, and 256–263, they cover obligations of States, Union directions, mutual delegation, All India Services, Public Service Commissions, and intergovernmental mechanisms. These relations shift during emergencies, while commissions and councils promote cooperative federalism and resolve disputes. | O84: 0000-00-00 00:00:00 | P84: 0000-00-00 00:00:00
A85: 156 | B85: GK | C85: English | D85: Centre–State Financial Relations: Taxation, Revenue Sharing, Grants, and Fiscal Control | E85: 5 | F85: =vlookup(E85,Category_ID!A:B,2,0) -> Polity and Governance | G85: 28 | H85: =vlookup(G85,Sub_Category_ID!A:C,3,0) -> Indian Constitution | I85: 66 | J85: =vlookup(I85,Section!A:D,4,0) -> Centre-State Relations | K85: 16c393fc7ca3c175415835ca3c3798df.jpg | M85: 1757500979_Centre–State Financial Relations_ Taxation, Revenue Sharing, Grants, and Fiscal Control.pdf | N85: The Indian Constitution’s Part XII (Articles 265–293) governs Centre–State financial relations, covering taxation powers, revenue distribution, grants, and borrowing limits. Taxing authority is split between Union and States, with GST introducing concurrent powers. The Finance Commission drives devolution, while Articles 275 and 282 govern grants. Persistent debates include vertical/horizontal imbalances, cesses, GST autonomy, and emergency fiscal powers.\r\n | O85: 0000-00-00 00:00:00 | P85: 0000-00-00 00:00:00
... A109: 180 | B109: GK | C109: English | D109: Government Policies and Schemes: Driving India’s Inclusive Growth and Development | E109: 5 | F109: =vlookup(E109,Category_ID!A:B,2,0) -> Polity and Governance | G109: 30 | H109: =vlookup(G109,Sub_Category_ID!A:C,3,0) -> Governance | I109: 54 | J109: =vlookup(I109,Section!A:D,4,0) -> Policies & Schemes | K109: 93175031a75f38c868abc3db450bc8e0.jpg | M109: 1757589385_Government Policies and Schemes_ Driving India’s Inclusive Growth and Development.pdf | N109: Government policies and schemes in India play a pivotal role in inclusive development by addressing health, housing, water, sanitation, employment, and infrastructure gaps. Flagship missions like Ayushman Bharat, PMAY, Jal Jeevan Mission, MGNREGA, PMGSY, and Swachh Bharat have transformed welfare delivery. Despite successes, challenges remain in targeting, leakages, sustainability, and equitable outcomes, demanding stronger monitoring and evaluation.\r\n | O109: 0000-00-00 00:00:00 | P109: 0000-00-00 00:00:00
A110: 181 | B110: GK | C110: English | D110: RTI and RTE: Strengthening Transparency and Access to Education | E110: 5 | F110: =vlookup(E110,Category_ID!A:B,2,0) -> Polity and Governance | G110: 30 | H110: =vlookup(G110,Sub_Category_ID!A:C,3,0) -> Governance | I110: 55 | J110: =vlookup(I110,Section!A:D,4,0) -> Rights Issues (RTI, RTE) | M110: 1757589708_RTI and RTE_ Strengthening Transparency and Access to Education.pdf | N110: The Right to Information (RTI) Act, 2005 ensures transparency and accountability in governance, while the Right to Education (RTE) Act, 2009 guarantees free, compulsory schooling for children aged 6–14. Together, they empower citizens and safeguard children’s rights. RTI strengthens RTE by exposing inefficiencies, enabling social audits, and ensuring that education rights are enforced in practice.\r\n | O110: 0000-00-00 00:00:00 | P110: 0000-00-00 00:00:00
A111: 182 | B111: GK | C111: English | D111: Panchayati Raj in India: Evolution, Structure, Challenges, and Democratic Role | E111: 5 | F111: =vlookup(E111,Category_ID!A:B,2,0) -> Polity and Governance | G111: 30 | H111: =vlookup(G111,Sub_Category_ID!A:C,3,0) -> Governance | I111: 56 | J111: =vlookup(I111,Section!A:D,4,0) -> Panchayati Raj | K111: 1f6ebe840bd0957f26dfc2ec4347aa09.jpeg | M111: 1757589819_Panchayati Raj in India_ Evolution, Structure, Challenges, and Democratic Role.pdf | N111: The Panchayati Raj system, formalised by the 73rd Constitutional Amendment (1992), institutionalises grassroots democracy through a three-tier structure — Gram Panchayat, Panchayat Samiti, and Zilla Parishad. It covers 29 subjects under the Eleventh Schedule and mandates elections, reservations, and Gram Sabha participation. Despite successes in decentralisation, Panchayats face challenges of inadequate devolution, financial weakness, and social inequalities, demanding further reforms.\r\n | O111: 0000-00-00 00:00:00 | P111: 0000-00-00 00:00:00
A112: 183 | B112: GK | C112: English | D112: Measuring India’s GDP: Growth Trends, Challenges, and Development Insights | E112: 6 | F112: =vlookup(E112,Category_ID!A:B,2,0) -> Indian Economy | G112: 31 | H112: =vlookup(G112,Sub_Category_ID!A:C,3,0) -> Basic Concepts | I112: 82 | J112: =vlookup(I112,Section!A:D,4,0) -> GDP( Gross Domestic Product) | K112: e71666a249e4d9692cfd3450b9f47d98.jpg | M112: 1757592353_Measuring India’s GDP_ Growth Trends, Challenges, and Development Insights.pdf | N112: Gross Domestic Product (GDP) is the total monetary value of all final goods and services produced within a country’s borders during a specific period (usually a quarter or a year), irrespective of who owns the production resources.India’s Gross Domestic Product (GDP) reflects the scale and dynamics of its economy, serving as a key measure of growth and development. Compiled by the National Statistical Office, GDP highlights sectoral strengths, expenditure patterns, and investment drivers. \r\n | O112: 0000-00-00 00:00:00 | P112: 0000-00-00 00:00:00
A113: 184 | B113: GK | C113: English | D113: Gross National Product: Measuring National Income in a Globalized World | E113: 6 | F113: =vlookup(E113,Category_ID!A:B,2,0) -> Indian Economy | G113: 31 | H113: =vlookup(G113,Sub_Category_ID!A:C,3,0) -> Basic Concepts | I113: 83 | J113: =vlookup(I113,Section!A:D,4,0) -> GNP(Gross National Product) | K113: e0d88d0d76011e440ad08581e19f1d0c.jpg | M113: 1757592508_Gross National Product_ Measuring National Income in a Globalized World.pdf | N113: Gross National Product (GNP), also known as Gross National Income (GNI), is defined as the total monetary value of all final goods and services produced by a nation’s residents, regardless of location, during a given year. Mathematically, GNP = GDP + Net Factor Income from Abroad (NFIA). It captures residents’ income better than GDP in today’s globalized economy of migration, FDI, and cross-border financial flows.\r\n | O113: 0000-00-00 00:00:00 | P113: 0000-00-00 00:00:00
A114: 185 | B114: GK | C114: English | D114: Net National Product: Economic Indicator Measuring National Wealth and Growth | E114: 6 | F114: =vlookup(E114,Category_ID!A:B,2,0) -> Indian Economy | G114: 31 | H114: =vlookup(G114,Sub_Category_ID!A:C,3,0) -> Basic Concepts | I114: 84 | J114: =vlookup(I114,Section!A:D,4,0) -> NNP(Net National Product) | K114: 6ee92df7815465aff7a28175935ff3de.png | M114: 1757593501_“Net National Product_ Economic Indicator Measuring National Wealth and Growth”.pdf | N114: Net National Product (NNP) is the total market value of all final goods and services produced by a country’s residents in a year, after accounting for depreciation of capital. NNP is a key indicator of economic performance, showing net production, guiding policy decisions, investment planning, and international economic comparisons, while highlighting the nation’s sustainable wealth generation capacity. | O114: 0000-00-00 00:00:00 | P114: 0000-00-00 00:00:00
A115: 186 | B115: GK | C115: English | D115: Net Domestic Product: Measuring Sustainable Economic Growth and Capital Utilization | E115: 6 | F115: =vlookup(E115,Category_ID!A:B,2,0) -> Indian Economy | G115: 31 | H115: =vlookup(G115,Sub_Category_ID!A:C,3,0) -> Basic Concepts | I115: 85 | J115: =vlookup(I115,Section!A:D,4,0) -> NDP(Net Domestic Product) | K115: ab6365aef6850b3dfd6b3eebd93144ba.png | M115: 1757666875_Net Domestic Product_ Measuring Sustainable Economic Growth and Capital Utilization.pdf | N115: Net Domestic Product (NDP) is the total market value of all final goods and services produced within a country, minus depreciation of capital assets. It indicates the sustainable economic output by showing how much of GDP remains after accounting for capital consumption. NDP helps policymakers, students, and researchers assess long-term growth and investment needs effectively.\r\n | O115: 0000-00-00 00:00:00 | P115: 0000-00-00 00:00:00
A116: 187 | B116: GK | C116: English | D116: Role of Money: Functions, Types, Importance, and Economic Stability Explained | E116: 6 | F116: =vlookup(E116,Category_ID!A:B,2,0) -> Indian Economy | G116: 31 | H116: =vlookup(G116,Sub_Category_ID!A:C,3,0) -> Basic Concepts | I116: 86 | J116: =vlookup(I116,Section!A:D,4,0) -> Money | K116: fc962cdfafd42de51192a495cf7c2d72.jpg | M116: 1757667175_Role of Money_ Functions, Types, Importance, and Economic Stability Explained.pdf | N116: Money is any widely accepted medium of exchange, serving as a unit of account, store of value, and standard for deferred payments. It facilitates trade, investment, and economic stability by influencing resource allocation, consumption, and fiscal policies. Its types include commodity, fiat, and digital money, each supporting diverse economic functions effectively.\r\n | O116: 0000-00-00 00:00:00 | P116: 0000-00-00 00:00:00
A117: 188 | B117: GK | C117: English | D117: Inflation in India: Causes, Consequences, and Government Control Measures | E117: 6 | F117: =vlookup(E117,Category_ID!A:B,2,0) -> Indian Economy | G117: 31 | H117: =vlookup(G117,Sub_Category_ID!A:C,3,0) -> Basic Concepts | I117: 87 | J117: =vlookup(I117,Section!A:D,4,0) -> Inflation | K117: 3b4e6c1239f780845d7ef20193643d90.jpeg | M117: 1757667300_Inflation in India_ Causes, Consequences, and Government Control Measures.pdf | N117: Inflation is the sustained rise in the general price level, reducing the purchasing power of money. In India, inflation is measured mainly through CPI and WPI. It arises from demand pressures, supply shocks, food price volatility, and global factors. Its effects range from eroding savings to reducing competitiveness. Government and RBI control inflation using monetary, fiscal, and supply-side measures.\r\n | O117: 0000-00-00 00:00:00 | P117: 0000-00-00 00:00:00
A118: 189 | B118: GK | C118: English | D118: Deflation in India: Causes, Impacts, Risks, and Policy Responses | E118: 6 | F118: =vlookup(E118,Category_ID!A:B,2,0) -> Indian Economy | G118: 31 | H118: =vlookup(G118,Sub_Category_ID!A:C,3,0) -> Basic Concepts | I118: 88 | J118: =vlookup(I118,Section!A:D,4,0) -> Deflation | K118: c07592d13535a030d7035dab2cc81f7c.jpg | M118: 1757667476_Deflation in India_ Causes, Impacts, Risks, and Policy Responses.pdf | N118: Deflation is a sustained fall in the general price level of goods and services. Though rare in India, it can occur due to weak demand, falling food prices, or global disinflation. Deflation risks include higher debt burdens, unemployment, and slower growth. Policymakers respond through monetary easing, fiscal stimulus, and structural safeguards to stabilize demand and maintain economic growth.\r\n | O118: 0000-00-00 00:00:00 | P118: 0000-00-00 00:00:00
A119: 190 | B119: GK | C119: English | D119: India’s Fiscal Policy: Spending, Tax Reforms, Growth, and Fiscal Consolidation | E119: 6 | F119: =vlookup(E119,Category_ID!A:B,2,0) -> Indian Economy | G119: 31 | H119: =vlookup(G119,Sub_Category_ID!A:C,3,0) -> Basic Concepts | I119: 89 | J119: =vlookup(I119,Section!A:D,4,0) -> Fiscal Policy | K119: 3aa1ec4c370a06b3665e17effd383ba3.jpg | M119: 1757668487_India’s Fiscal Policy_ Spending, Tax Reforms, Growth, and Fiscal Consolidation.pdf | N119: Fiscal policy refers to government decisions on spending, taxation, borrowing, and transfers to regulate growth, employment, and stability. Fiscal policy is the backbone of India’s economic strategy. It influences demand, supports welfare, builds infrastructure, and ensures inclusive growth. \r\n | O119: 0000-00-00 00:00:00 | P119: 0000-00-00 00:00:00
A120: 191 | B120: GK | C120: English | D120: RBI’s Monetary Policy: Inflation Control, Liquidity Management, and Financial Stability | E120: 6 | F120: =vlookup(E120,Category_ID!A:B,2,0) -> Indian Economy | G120: 31 | H120: =vlookup(G120,Sub_Category_ID!A:C,3,0) -> Basic Concepts | I120: 90 | J120: =vlookup(I120,Section!A:D,4,0) -> Monetary Policy | K120: 6224c0937c2a55bfb52b1030b1241326.jpg | M120: 1757668630_RBI’s Monetary Policy_ Inflation Control, Liquidity Management, and Financial Stability.pdf | N120: Monetary policy is the process by which a country’s central bank, in India the Reserve Bank of India (RBI), manages money supply and credit conditions using tools like policy rates, reserve requirements, and open market operations. Its objectives are to control inflation, maintain adequate liquidity, and ensure financial stability, thereby supporting sustainable economic growth.\r\n | O120: 0000-00-00 00:00:00 | P120: 0000-00-00 00:00:00
A121: 192 | B121: GK | C121: English | D121: India’s Downturn: Causes, Socioeconomic Consequences, and Multi-front Recovery Strategies | E121: 6 | F121: =vlookup(E121,Category_ID!A:B,2,0) -> Indian Economy | G121: 31 | H121: =vlookup(G121,Sub_Category_ID!A:C,3,0) -> Basic Concepts | I121: 91 | J121: =vlookup(I121,Section!A:D,4,0) -> NPAs( Non-Performing Asset) | K121: 7e5ac351c7bc2e57d6d57307904d6ab6.jpg | M121: 1757669736_India’s Downturn_ Causes, Socioeconomic Consequences, and Multi-front Recovery Strategies.pdf | N121: An economic downturn is a prolonged slowdown in economic activity, reflected in weaker GDP, declining consumption, reduced investment, rising unemployment, and fiscal strain. In India, downturns stem from weak demand, credit stress, external shocks, and structural constraints. They erode growth and jobs but can be mitigated through calibrated short-term stimulus, financial stability measures, and medium-to-long-term structural reforms fostering inclusive and resilient growth.\r\n | O121: 0000-00-00 00:00:00 | P121: 0000-00-00 00:00:00
A122: 193 | B122: GK | C122: English | D122: Two-Slab GST Reform: Simplifying Indirect Taxation for Unified India | E122: 6 | F122: =vlookup(E122,Category_ID!A:B,2,0) -> Indian Economy | G122: 31 | H122: =vlookup(G122,Sub_Category_ID!A:C,3,0) -> Basic Concepts | I122: 92 | J122: =vlookup(I122,Section!A:D,4,0) -> GST(Goods & Services Tax) | K122: 909035272c1908d17c769ac567c88506.jpg | M122: 1757669935_Two-Slab GST Reform_ Simplifying Indirect Taxation for Unified India.pdf | N122: Definition: Indirect taxation is a tax levied on goods and services rather than income, collected at points of sale or import. GST (Goods and Services Tax) is India’s unified indirect tax, introduced in 2017, comprising CGST (Central GST), SGST (State GST), IGST (Integrated GST), and UTGST (Union Territory GST).\r\n | O122: 0000-00-00 00:00:00 | P122: 0000-00-00 00:00:00
... A232: 311 | B232: GK | C232: Hindi | D232: रोहित शर्मा: शानदार ओपनर, छक्कों का बादशाह और भारत का हिटमैन | E232: 11 | F232: =vlookup(E232,Category_ID!A:B,2,0) -> Static GK | G232: 37 | H232: =vlookup(G232,Sub_Category_ID!A:C,3,0) -> Famous Personalities | I232: 119 | J232: =vlookup(I232,Section!A:D,4,0) -> Sportspersons | K232: bfcb8fa2504f87de970c891eb0866ee9.jpg | M232: 1758284590_रोहित शर्मा_ शानदार ओपनर, छक्कों का बादशाह और भारत का हिटमैन (310).pdf | N232: रोहित शर्मा, जिन्हें \"हिटमैन\" कहा जाता है, भारत के गतिशील ओपनर और मौजूदा कप्तान हैं। 1987 में जन्मे रोहित ने मुंबई क्रिकेट से अंतरराष्ट्रीय स्तर तक का सफर तय किया। तीन वनडे दोहरे शतक समेत अनेक विश्व रिकॉर्ड उनके नाम हैं। एक आकर्षक बल्लेबाज़ और छक्कों के महारथी, उन्होंने भारत और मुंबई इंडियंस को सफलता की नई ऊँचाइयों पर पहुँचाया।\r\n | O232: 0000-00-00 00:00:00 | P232: 0000-00-00 00:00:00
A233: 313 | B233: GK | C233: Hindi | D233: साम्राज्य से गणराज्य तक: भारतीय संविधान की ऐतिहासिक यात्रा | E233: 5 | F233: =vlookup(E233,Category_ID!A:B,2,0) -> Polity and Governance | G233: 28 | H233: =vlookup(G233,Sub_Category_ID!A:C,3,0) -> Indian Constitution | I233: 46 | J233: =vlookup(I233,Section!A:D,4,0) -> Making of the Constitution | M233: 1758354540__साम्राज्य से गणराज्य तक_ भारतीय संविधान की ऐतिहासिक यात्रा.pdf | N233: भारतीय संविधान की जड़ें दो शताब्दियों से फैली हैं—ब्रिटिश उपनिवेशी कानूनों से लेकर स्वशासन की माँग करने वाले राष्ट्रीय आंदोलनों तक। प्रमुख चरणों में भारत शासन अधिनियम, नेहरू रिपोर्ट, गोलमेज सम्मेलन और 1935 का अधिनियम शामिल हैं। 1946–49 की संविधान सभा की बहसें, डॉ. बी.आर. अंबेडकर सहित नेताओं के मार्गदर्शन में, 26 नवंबर 1949 को संप्रभु, लोकतांत्रिक और समावेशी संविधान में परिणत हुईं।\r\n | O233: 0000-00-00 00:00:00 | P233: 0000-00-00 00:00:00
A234: 315 | B234: GK | C234: Hindi | D234: संविधान सभा: समितियों और सहमति से भारत का संविधान निर्माण | E234: 5 | F234: =vlookup(E234,Category_ID!A:B,2,0) -> Polity and Governance | G234: 28 | H234: =vlookup(G234,Sub_Category_ID!A:C,3,0) -> Indian Constitution | I234: 46 | J234: =vlookup(I234,Section!A:D,4,0) -> Making of the Constitution | M234: 1758354760_संविधान सभा_ समितियों और सहमति से भारत का संविधान निर्माण.pdf | N234: भारत की संविधान सभा (1946–1950) ने संविधान को सुनियोजित बहसों, विशेषज्ञ समितियों और सावधानीपूर्वक प्रारूपण के माध्यम से तैयार किया। प्रारंभिक 389 सदस्यों वाली सभा ने 165 दिनों में 11 सत्र किए। डॉ. बी.आर. अम्बेडकर, जवाहरलाल नेहरू और सरदार पटेल जैसे नेताओं के नेतृत्व में हजारों संशोधनों पर विचार कर लोकतांत्रिक, संघीय और अधिकार-आधारित शासन ढांचा स्थापित किया गया।\r\n | O234: 0000-00-00 00:00:00 | P234: 0000-00-00 00:00:00
A235: 317 | B235: GK | C235: Hindi | D235: भारत के अनोखे और व्यापक संविधान के वैश्विक प्रेरणा स्रोत | E235: 5 | F235: =vlookup(E235,Category_ID!A:B,2,0) -> Polity and Governance | G235: 28 | H235: =vlookup(G235,Sub_Category_ID!A:C,3,0) -> Indian Constitution | I235: 46 | J235: =vlookup(I235,Section!A:D,4,0) -> Making of the Constitution | M235: 1758355603_भारत के अनोखे और व्यापक संविधान के वैश्विक प्रेरणा स्रोत.pdf | N235: 1950 में अंगीकृत भारतीय संविधान, वैश्विक आदर्शों और शासकीय मॉडलों का एक संगम है, जिसे भारतीय परिस्थितियों के अनुरूप ढाला गया। इसमें 1935 के भारत सरकार अधिनियम, तथा अमेरिका, ब्रिटेन, कनाडा, आयरलैंड, ऑस्ट्रेलिया, फ्रांस और अन्य देशों के संविधानों से विशेषताएँ ली गईं। इसने लोकतंत्र, संघवाद, न्याय और अधिकारों को मिलाकर विश्व के सबसे बड़े लोकतंत्र के लिए एक सुदृढ़ ढाँचा प्रस्तुत किया।\r\n | O235: 0000-00-00 00:00:00 | P235: 0000-00-00 00:00:00
A236: 319 | B236: GK | C236: Hindi | D236: भारतीय संविधान का अंगीकरण और प्रमुख विशेषताएँ विस्तृत रूप में | E236: 5 | F236: =vlookup(E236,Category_ID!A:B,2,0) -> Polity and Governance | G236: 28 | H236: =vlookup(G236,Sub_Category_ID!A:C,3,0) -> Indian Constitution | I236: 46 | J236: =vlookup(I236,Section!A:D,4,0) -> Making of the Constitution | M236: 1758356415_भारतीय संविधान का अंगीकरण और प्रमुख विशेषताएँ विस्तृत रूप में.pdf | N236: भारतीय संविधान को 26 नवम्बर 1949 को अंगीकृत किया गया। कुछ प्रावधान तुरंत लागू हुए, जबकि शेष 26 जनवरी 1950 से प्रभावी हुए, जिसे आज गणतंत्र दिवस के रूप में मनाया जाता है। विश्व का सबसे लंबा लिखित संविधान होने के नाते यह संघीय और एकात्मक तत्वों का मिश्रण है। इसमें अधिकार, कर्तव्य, संसदीय लोकतंत्र और विविधता के अनुरूप वैश्विक सिद्धांतों का समावेश है।\r\n | O236: 0000-00-00 00:00:00 | P236: 0000-00-00 00:00:00
A237: 321 | B237: GK | C237: Hindi | D237: भारत का प्रस्तावना: संप्रभुता, न्याय, स्वतंत्रता, समानता और बंधुता का आधार | E237: 5 | F237: =vlookup(E237,Category_ID!A:B,2,0) -> Polity and Governance | G237: 28 | H237: =vlookup(G237,Sub_Category_ID!A:C,3,0) -> Indian Constitution | I237: 47 | J237: =vlookup(I237,Section!A:D,4,0) -> Preamble | M237: 1758356819_भारत का प्रस्तावना_ संप्रभुता, न्याय, स्वतंत्रता, समानता और बंधुता का आधार.pdf | N237: भारतीय संविधान की प्रस्तावना राष्ट्र के मूल्यों को दर्शाती है—संप्रभुता, समाजवाद, धर्मनिरपेक्षता, लोकतंत्र और गणराज्य। यह न्याय, स्वतंत्रता, समानता और बंधुता को मार्गदर्शक सिद्धांत घोषित करती है। 42वें संशोधन द्वारा जोड़े गए शब्द शासन और विधि को आकार देते हैं। यद्यपि यह प्रत्यक्ष रूप से लागू नहीं है, न्यायालय व्याख्या हेतु इसका उपयोग करते हैं, जिससे यह भारत की संवैधानिक दर्शन की आधारशिला बन जाती है।\r\n | O237: 0000-00-00 00:00:00 | P237: 0000-00-00 00:00:00
A238: 323 | B238: GK | C238: Hindi | D238: भारत की प्रस्तावना: इतिहास, संशोधन और सर्वोच्च न्यायालय की व्याख्या | E238: 5 | F238: =vlookup(E238,Category_ID!A:B,2,0) -> Polity and Governance | G238: 28 | H238: =vlookup(G238,Sub_Category_ID!A:C,3,0) -> Indian Constitution | I238: 47 | J238: =vlookup(I238,Section!A:D,4,0) -> Preamble | M238: 1758357197_भारत की प्रस्तावना_ इतिहास, संशोधन और सर्वोच्च न्यायालय की व्याख्या.pdf | N238: भारतीय संविधान की प्रस्तावना में केवल एक बार संशोधन हुआ है, 1976 के 42वें संशोधन द्वारा, जिसमें “समाजवादी,” “धर्मनिरपेक्ष,” और “अखंडता” जोड़े गए। सर्वोच्च न्यायालय के ऐतिहासिक निर्णयों ने इसे संविधान का हिस्सा माना और इसकी मूल संरचना को सुरक्षित रखा। हाल की बहसों में इन शब्दों को हटाने की मांग उठी, पर न्यायालय ने उनके बने रहने को सही ठहराया।\r\n | O238: 0000-00-00 00:00:00 | P238: 0000-00-00 00:00:00
A239: 325 | B239: GK | C239: Hindi | D239: सर्वोच्च न्यायालय ने संविधान में प्रस्तावना की भूमिका पुष्ट की | E239: 5 | F239: =vlookup(E239,Category_ID!A:B,2,0) -> Polity and Governance | G239: 28 | H239: =vlookup(G239,Sub_Category_ID!A:C,3,0) -> Indian Constitution | I239: 47 | J239: =vlookup(I239,Section!A:D,4,0) -> Preamble | M239: 1758357367_सर्वोच्च न्यायालय ने संविधान में प्रस्तावना की भूमिका पुष्ट की.pdf | N239: भारत के सर्वोच्च न्यायालय ने प्रस्तावना पर अपने दृष्टिकोण को विकसित किया—बेहरुबरी मामले में इसे गैर-प्रचालनात्मक मानने से लेकर केशवानंद भारती (1973) में इसे संविधान का हिस्सा स्वीकार करने तक। संशोधन योग्य होते हुए भी यह व्याख्या का मार्गदर्शक और मूल संरचना का संकेतक है। ऐतिहासिक फैसलों ने धर्मनिरपेक्षता, समाजवाद, लोकतंत्र और अधिकारों व निदेशक सिद्धांतों के संतुलन को सुरक्षित रखा।\r\n | O239: 0000-00-00 00:00:00 | P239: 0000-00-00 00:00:00
A240: 326 | B240: GK | C240: English | D240: Virat Kohli: Modern Cricket Icon, Run Machine, and Leader | E240: 11 | F240: =vlookup(E240,Category_ID!A:B,2,0) -> Static GK | G240: 37 | H240: =vlookup(G240,Sub_Category_ID!A:C,3,0) -> Famous Personalities | I240: 119 | J240: =vlookup(I240,Section!A:D,4,0) -> Sportspersons | K240: 731c63ca11490a0637d80d385b596565.jpg | M240: 1758357398_Virat Kohli_ Modern Cricket Icon, Run Machine, and Leader.pdf | N240: Virat Kohli is India’s star batsman, known for his aggressive play and unmatched consistency across formats. Born in Delhi in 1988, he rose to fame after leading India to U-19 World Cup victory in 2008. A former captain in all formats, Kohli holds numerous batting records and remains a key figure in world cricket, admired for fitness and fierce competitiveness.\r\n | O240: 0000-00-00 00:00:00 | P240: 0000-00-00 00:00:00
A241: 328 | B241: GK | C241: Hindi | D241: भारत में मौलिक अधिकार: परिभाषा, वर्गीकरण और संवैधानिक संरक्षण | E241: 5 | F241: =vlookup(E241,Category_ID!A:B,2,0) -> Polity and Governance | G241: 28 | H241: =vlookup(G241,Sub_Category_ID!A:C,3,0) -> Indian Constitution | I241: 48 | J241: =vlookup(I241,Section!A:D,4,0) -> Fundamental Rights & Duties | M241: 1758357607_भारत में मौलिक अधिकार_ परिभाषा, वर्गीकरण और संवैधानिक संरक्षण.pdf | N241: भारतीय संविधान के भाग III (अनुच्छेद 12–35) में मौलिक अधिकार दिए गए हैं, जो समानता, स्वतंत्रता और न्याय सुनिश्चित करते हैं। छह वर्गों में विभाजित ये अधिकार नागरिकों को राज्य के दुरुपयोग से बचाते हैं और लोकतांत्रिक मूल्यों की रक्षा करते हैं। ये न्यायालयों द्वारा प्रवर्तनीय हैं, यथोचित प्रतिबंधों के अधीन हैं, और कमजोर वर्गों के लिए विशेष सुरक्षा प्रदान करते हैं।\r\n | O241: 0000-00-00 00:00:00 | P241: 0000-00-00 00:00:00
A242: 330 | B242: GK | C242: Hindi | D242: विराट कोहली: आधुनिक क्रिकेट आइकन, रन मशीन और कप्तान | E242: 11 | F242: =vlookup(E242,Category_ID!A:B,2,0) -> Static GK | G242: 37 | H242: =vlookup(G242,Sub_Category_ID!A:C,3,0) -> Famous Personalities | I242: 119 | J242: =vlookup(I242,Section!A:D,4,0) -> Sportspersons | K242: 0417f2fced75ffbb9e320fe73cdd4f85.jpg | M242: 1758357835_विराट कोहली_ आधुनिक क्रिकेट आइकन, रन मशीन और कप्तान (326).pdf | N242: विराट कोहली भारत के स्टार बल्लेबाज हैं, जो आक्रामक खेल और सभी प्रारूपों में अद्वितीय स्थिरता के लिए जाने जाते हैं। 1988 में दिल्ली में जन्मे कोहली ने 2008 में U-19 वर्ल्ड कप जीतकर प्रसिद्धि पाई। सभी प्रारूपों में पूर्व कप्तान, कोहली के पास कई बल्लेबाजी रिकॉर्ड हैं और वे फिटनेस, प्रतिस्पर्धात्मकता और क्रिकेट में निष्ठा के लिए विश्व स्तर पर प्रशंसित हैं।\r\n | O242: 0000-00-00 00:00:00 | P242: 0000-00-00 00:00:00
A243: 331 | B243: GK | C243: Hindi | D243: अधिकारों की रक्षा: भारत में रिट, प्रतिबंध और संवैधानिक उपाय | E243: 5 | F243: =vlookup(E243,Category_ID!A:B,2,0) -> Polity and Governance | G243: 28 | H243: =vlookup(G243,Sub_Category_ID!A:C,3,0) -> Indian Constitution | I243: 48 | J243: =vlookup(I243,Section!A:D,4,0) -> Fundamental Rights & Duties | M243: 1758357917_अधिकारों की रक्षा_ भारत में रिट, प्रतिबंध और संवैधानिक उपाय.pdf | N243: भारत में मौलिक अधिकारों की रक्षा अनुच्छेद 32 और 226 के अंतर्गत जारी रिटों द्वारा की जाती है। हेबियस कॉर्पस, मंडामस, प्रोहीबिशन, सर्टियोरारी और क्वो वारंटो जैसे संवैधानिक उपाय नागरिकों को अवैध कार्यवाही से बचाते हैं। परंतु अधिकार पूर्ण नहीं हैं; संप्रभुता, सुरक्षा और सार्वजनिक व्यवस्था हेतु उचित प्रतिबंध लगाए जाते हैं। महत्वपूर्ण मामलों ने स्वतंत्रता और राज्य-नियंत्रण के बीच संतुलन स्थापित किया। | O243: 0000-00-00 00:00:00 | P243: 0000-00-00 00:00:00
A244: 332 | B244: GK | C244: English | D244: MS Dhoni: India’s Captain Cool and World Cup Hero | E244: 11 | F244: =vlookup(E244,Category_ID!A:B,2,0) -> Static GK | G244: 37 | H244: =vlookup(G244,Sub_Category_ID!A:C,3,0) -> Famous Personalities | I244: 119 | J244: =vlookup(I244,Section!A:D,4,0) -> Sportspersons | K244: b7fecbb6708b61eb619e4df82e0e9b00.jpg | M244: 1758357999_MS Dhoni_ India’s Captain Cool and World Cup Hero.pdf | N244: Mahendra Singh Dhoni, India’s most successful cricket captain, redefined leadership with calmness and strategy. Born in Ranchi in 1981, he rose from a small-town boy to a cricketing icon. He led India to victories in T20 (2007) and ODI (2011) World Cups and Champions Trophy (2013). Known for sharp wicketkeeping, powerful finishing, and cool-headed leadership, Dhoni remains an enduring legend.\r\n | O244: 0000-00-00 00:00:00 | P244: 0000-00-00 00:00:00
A245: 333 | B245: GK | C245: Hindi | D245: एम.एस. धोनी: भारत के कप्तान कूल और वर्ल्ड कप हीरो | E245: 11 | F245: =vlookup(E245,Category_ID!A:B,2,0) -> Static GK | G245: 37 | H245: =vlookup(G245,Sub_Category_ID!A:C,3,0) -> Famous Personalities | I245: 119 | J245: =vlookup(I245,Section!A:D,4,0) -> Sportspersons | K245: 3b54ca5352c34e303e66a4094e4c7941.jpg | M245: 1758358165_एम.एस. धोनी_ भारत के कप्तान कूल और वर्ल्ड कप हीरो (332).pdf | N245: महेंद्र सिंह धोनी, भारत के सबसे सफल क्रिकेट कप्तान, ने अपनी शांतचित्त और रणनीतिक नेतृत्व शैली से क्रिकेट की परिभाषा बदल दी। 1981 में रांची में जन्मे, उन्होंने छोटे शहर के लड़के से क्रिकेट आइकन बनने तक का सफर तय किया। उन्होंने भारत को T20 (2007), ODI (2011) वर्ल्ड कप और चैंपियंस ट्रॉफी (2013) में जीत दिलाई। तेज विकेटकीपिंग, शक्तिशाली फिनिशिंग और शांत नेतृत्व के लिए जाने जाते हैं।\r\n | O245: 0000-00-00 00:00:00 | P245: 0000-00-00 00:00:00
A246: 334 | B246: GK | C246: English | D246: Anil Kumble: Spin Wizard, Coach, and Indian Cricket Legend | E246: 11 | F246: =vlookup(E246,Category_ID!A:B,2,0) -> Static GK | G246: 37 | H246: =vlookup(G246,Sub_Category_ID!A:C,3,0) -> Famous Personalities | I246: 119 | J246: =vlookup(I246,Section!A:D,4,0) -> Sportspersons | K246: 78eb90c082c4086f1f87029f9421ee95.jpg | M246: 1758359066_Anil Kumble_ Spin Wizard, Coach, and Indian Cricket Legend__.pdf | N246: Anil Kumble, India’s highest wicket-taker in Test cricket, was a legendary leg-spinner renowned for accuracy and perseverance. Born in Bangalore in 1970, he played for India from 1990 to 2008. Known for his 10-wicket haul in an innings, Kumble later served as captain and coach. His post-retirement contributions continue to shape Indian cricket’s infrastructure and ethics.\r\n | O246: 0000-00-00 00:00:00 | P246: 0000-00-00 00:00:00
A247: 335 | B247: GK | C247: Hindi | D247: अनिल कुंबले: स्पिन के जादूगर, कोच और भारतीय दिग्गज | E247: 11 | F247: =vlookup(E247,Category_ID!A:B,2,0) -> Static GK | G247: 37 | H247: =vlookup(G247,Sub_Category_ID!A:C,3,0) -> Famous Personalities | I247: 119 | J247: =vlookup(I247,Section!A:D,4,0) -> Sportspersons | K247: 8140645d45761a84d2eb6f0ffc1a1276.jpg | M247: 1758359417_अनिल कुंबले_ स्पिन के जादूगर, कोच और भारतीय दिग्गज (334).pdf | N247: अनिल कुंबले, भारत के सर्वाधिक टेस्ट विकेट लेने वाले दिग्गज लेग स्पिनर थे, जो अपनी सटीकता और धैर्य के लिए प्रसिद्ध रहे। 1970 में बेंगलुरु में जन्मे, उन्होंने 1990 से 2008 तक भारत का प्रतिनिधित्व किया। पाकिस्तान के खिलाफ 10 विकेट लेने की ऐतिहासिक उपलब्धि के अलावा, उन्होंने कप्तान और कोच के रूप में भी योगदान दिया। सेवानिवृत्ति के बाद भी वे भारतीय क्रिकेट के ढांचे और मूल्यों को आकार दे रहे हैं।\r\n | O247: 0000-00-00 00:00:00 | P247: 0000-00-00 00:00:00
A248: 336 | B248: GK | C248: English | D248: Rahul Dravid: The Wall of Indian Cricket and Discipline | E248: 11 | F248: =vlookup(E248,Category_ID!A:B,2,0) -> Static GK | G248: 37 | H248: =vlookup(G248,Sub_Category_ID!A:C,3,0) -> Famous Personalities | I248: 119 | J248: =vlookup(I248,Section!A:D,4,0) -> Sportspersons | K248: 128034c9176ffdb1c66e0a4fc164cdf9.jpg | M248: 1758359605_Rahul Dravid_ The Wall of Indian Cricket and Discipline.pdf | N248: Rahul Dravid, known as \"The Wall\", is one of India’s greatest Test batsmen. Born in 1973, he represented India from 1996 to 2012. Admired for his technique, patience, and sportsmanship, Dravid scored over 24,000 international runs. Post-retirement, he has contributed immensely to Indian cricket as a coach and mentor, shaping the next generation of cricketers.\r\n | O248: 0000-00-00 00:00:00 | P248: 0000-00-00 00:00:00
A249: 337 | B249: GK | C249: Hindi | D249: राहुल द्रविड़: भारतीय क्रिकेट की दीवार और अनुशासन के प्रतीक | E249: 11 | F249: =vlookup(E249,Category_ID!A:B,2,0) -> Static GK | G249: 37 | H249: =vlookup(G249,Sub_Category_ID!A:C,3,0) -> Famous Personalities | I249: 119 | J249: =vlookup(I249,Section!A:D,4,0) -> Sportspersons | K249: a08d5af0d28279eb4c6e425b1ce95445.jpg | M249: 1758359784_राहुल द्रविड़_ भारतीय क्रिकेट की दीवार और अनुशासन के प्रतीक (336).pdf | N249: राहुल द्रविड़, जिन्हें “द वॉल” कहा जाता है, भारत के महानतम टेस्ट बल्लेबाजों में गिने जाते हैं। 1973 में जन्मे द्रविड़ ने 1996 से 2012 तक भारत का प्रतिनिधित्व किया। बेहतरीन तकनीक, धैर्य और खेलभावना के लिए प्रसिद्ध, उन्होंने अंतरराष्ट्रीय क्रिकेट में 24,000 से अधिक रन बनाए। संन्यास के बाद वे कोच और मेंटर के रूप में नई पीढ़ी को दिशा दे रहे हैं। | O249: 0000-00-00 00:00:00 | P249: 0000-00-00 00:00:00
A250: 338 | B250: GK | C250: English | D250: Sachin Tendulkar: India’s Cricketing God and Run-Making Legend | E250: 11 | F250: =vlookup(E250,Category_ID!A:B,2,0) -> Static GK | G250: 37 | H250: =vlookup(G250,Sub_Category_ID!A:C,3,0) -> Famous Personalities | I250: 119 | J250: =vlookup(I250,Section!A:D,4,0) -> Sportspersons | K250: 7c7e0d3a36318f7d2a5afbdc67477a26.jpeg | M250: 1758360319_Sachin Tendulkar_ India’s Cricketing God and Run-Making Legend.pdf | N250: Sachin Tendulkar, India’s greatest cricketer, debuted at 16 and became the highest run-scorer in both Tests and ODIs. Known as the \"Master Blaster\", he scored 100 international centuries and inspired generations. He led India to its 2011 World Cup win and later served as a Rajya Sabha MP. A Bharat Ratna recipient, his cricketing legacy is unmatched.\r\n | O250: 0000-00-00 00:00:00 | P250: 0000-00-00 00:00:00
A251: 339 | B251: GK | C251: Hindi | D251: सचिन तेंदुलकर: भारत का क्रिकेट देवता और रन बनाने वाला महानायक | E251: 11 | F251: =vlookup(E251,Category_ID!A:B,2,0) -> Static GK | G251: 37 | H251: =vlookup(G251,Sub_Category_ID!A:C,3,0) -> Famous Personalities | I251: 119 | J251: =vlookup(I251,Section!A:D,4,0) -> Sportspersons | K251: d2e52b772284994e3372188309cce6f3.jpeg | M251: 1758360607_सचिन तेंदुलकर_ भारत का क्रिकेट देवता और रन बनाने वाला महानायक (338).pdf | N251: सचिन तेंदुलकर, भारत के सबसे महान क्रिकेटर, ने 16 वर्ष की उम्र में पदार्पण किया और टेस्ट व वनडे दोनों में सर्वाधिक रन बनाने वाले बने। \"मास्टर ब्लास्टर\" कहलाने वाले सचिन ने 100 अंतर्राष्ट्रीय शतक जड़े और पीढ़ियों को प्रेरित किया। उन्होंने भारत को 2011 विश्व कप जिताया और बाद में राज्यसभा सांसद बने। भारत रत्न से सम्मानित, उनकी क्रिकेट विरासत अनुपम है।\r\n | O251: 0000-00-00 00:00:00 | P251: 0000-00-00 00:00:00
A252: 340 | B252: GK | C252: English | D252: Sunil Gavaskar: India’s First Batting Legend and Test Run Machine | E252: 11 | F252: =vlookup(E252,Category_ID!A:B,2,0) -> Static GK | G252: 37 | H252: =vlookup(G252,Sub_Category_ID!A:C,3,0) -> Famous Personalities | I252: 119 | J252: =vlookup(I252,Section!A:D,4,0) -> Sportspersons | K252: 246ea788fee85c18c7e7cdfde517ac7e.jpg | M252: 1758360746_Sunil Gavaskar_ India’s First Batting Legend and Test Run Machine.pdf | N252: Sunil Gavaskar, born in 1949, is India’s first batting superstar and the first cricketer to score 10,000 Test runs. Known for his technique against fast bowling, he redefined Indian cricket in the 1970s–80s. A former captain and cricket commentator, Gavaskar has received the Padma Bhushan and ICC Hall of Fame honors for his extraordinary contributions.\r\n | O252: 0000-00-00 00:00:00 | P252: 0000-00-00 00:00:00
A253: 341 | B253: GK | C253: Hindi | D253: सुनील गावस्कर: भारत के पहले बल्लेबाजी महानायक और टेस्ट रन मशीन | E253: 11 | F253: =vlookup(E253,Category_ID!A:B,2,0) -> Static GK | G253: 37 | H253: =vlookup(G253,Sub_Category_ID!A:C,3,0) -> Famous Personalities | I253: 119 | J253: =vlookup(I253,Section!A:D,4,0) -> Sportspersons | K253: 7b120cf260f7f9745774f03a71e7741b.jpg | M253: 1758360957_सुनील गावस्कर_ भारत के पहले बल्लेबाजी महानायक और टेस्ट रन मशीन (340).pdf | N253: सुनील गावस्कर, 1949 में जन्मे, भारत के पहले बल्लेबाजी सुपरस्टार और 10,000 टेस्ट रन बनाने वाले पहले क्रिकेटर हैं। तेज गेंदबाजी के खिलाफ अपनी तकनीक के लिए प्रसिद्ध, उन्होंने 1970–80 के दशक में भारतीय क्रिकेट की परिभाषा बदली। पूर्व कप्तान और क्रिकेट विश्लेषक रहे गावस्कर को पद्म भूषण और आईसीसी हॉल ऑफ फेम सम्मान उनके असाधारण योगदानों के लिए मिला।\r\n | O253: 0000-00-00 00:00:00 | P253: 0000-00-00 00:00:00
A254: 342 | B254: GK | C254: English | D254: Kapil Dev: India’s First World Champion Captain and Legendary All-Rounder | E254: 11 | F254: =vlookup(E254,Category_ID!A:B,2,0) -> Static GK | G254: 37 | H254: =vlookup(G254,Sub_Category_ID!A:C,3,0) -> Famous Personalities | I254: 119 | J254: =vlookup(I254,Section!A:D,4,0) -> Sportspersons | K254: e83f5740e04be6ff63f1c2eff69f7bd7.jpg | M254: 1758361545_Kapil Dev_ India’s First World Champion Captain and Legendary All-Rounder.pdf | N254: Kapil Dev, born in 1959, is a legendary Indian all-rounder who led India to its historic 1983 Cricket World Cup win. With 434 Test wickets and 5000+ runs, he redefined fast bowling and inspired a generation. Post-retirement, he served as India’s coach and remains an influential voice in sports. He’s received top national honors, including the Padma Bhushan.\r\n | O254: 0000-00-00 00:00:00 | P254: 0000-00-00 00:00:00
A255: 343 | B255: GK | C255: Hindi | D255: कपिल देव: भारत के पहले विश्वविजेता कप्तान और महान ऑलराउंडर | E255: 11 | F255: =vlookup(E255,Category_ID!A:B,2,0) -> Static GK | G255: 37 | H255: =vlookup(G255,Sub_Category_ID!A:C,3,0) -> Famous Personalities | I255: 119 | J255: =vlookup(I255,Section!A:D,4,0) -> Sportspersons | K255: bc2cc97985b7ed036d084dced2cff1bd.jpg | M255: 1758361867_कपिल देव_ भारत के पहले विश्वविजेता कप्तान और महान ऑलराउंडर (342).pdf | N255: कपिल देव, 1959 में जन्मे, भारत के महान ऑलराउंडर और 1983 विश्व कप विजेता कप्तान हैं। 434 टेस्ट विकेट और 5000+ रन बनाकर उन्होंने भारतीय तेज गेंदबाजी को नई पहचान दी। संन्यास के बाद कोच और क्रिकेट विश्लेषक बने। उन्हें पद्म भूषण समेत कई सम्मान मिले। उनका योगदान भारतीय क्रिकेट के इतिहास में अमिट है।\r\n | O255: 0000-00-00 00:00:00 | P255: 0000-00-00 00:00:00
...

Sheet Category_ID
A1: id | B1: category_name | C1: status | D1: created_at
A2: 1 | B2: Indian History | C2: 1 | D2: 45905.642
A3: 2 | B3: Indian Geography | C3: 1 | D3: 45905.642
A4: 3 | B4: World Geography | C4: 1 | D4: 45905.642
A5: 4 | B5: Map Work | C5: 1 | D5: 45905.642
A6: 5 | B6: Polity and Governance | C6: 1 | D6: 45905.642
A7: 6 | B7: Indian Economy | C7: 1 | D7: 45905.642
A8: 7 | B8: General Science | C8: 1 | D8: 45905.642
A9: 8 | B9: Environment and Ecology | C9: 1 | D9: 45905.642
A10: 9 | B10: Indian Art and Culture | C10: 1 | D10: 45905.642
A11: 10 | B11: International Relations | C11: 1 | D11: 45905.642
A12: 11 | B12: Static GK | C12: 1 | D12: 45905.642
A13: 12 | B13: Science and Technology | C13: 1 | D13: 45905.642
... A17: 16 | B17: Verbal Ability | C17: 1 | D17: 45905.642

Sheet Sub_Category_ID
A1: id | B1: category_id | C1: sub_category_name | D1: status | E1: created_at
A2: 2 | B2: 1 | C2: Medieval History | D2: 1 | E2: 45905.707
A3: 3 | B3: 1 | C3: Modern History | D3: 1 | E3: 45906.52
A4: 21 | B4: 1 | C4: Ancient History | D4: 1 | E4: 45907.439
A5: 25 | B5: 2 | C5: Physical Geography | D5: 1 | E5: 45908.193
A6: 26 | B6: 2 | C6: Human Geography | D6: 1 | E6: 45908.193
A7: 27 | B7: 2 | C7: Economic Geography | D7: 1 | E7: 45908.193
A8: 28 | B8: 5 | C8: Indian Constitution | D8: 1 | E8: 45908.461
A9: 29 | B9: 5 | C9: Indian Political System | D9: 1 | E9: 45908.462
A10: 30 | B10: 5 | C10: Governance | D10: 1 | E10: 45908.463
A11: 31 | B11: 6 | C11: Basic Concepts | D11: 1 | E11: 45911.482
A12: 32 | B12: 6 | C12: Sectors of Economy | D12: 1 | E12: 45911.483
A13: 33 | B13: 6 | C13: Government Schemes & Reforms | D13: 1 | E13: 45911.483
... A30: 51 | B30: 16 | C30: Verbal Ability | D30: 1 | E30: 45975.269

Sheet Section
A1: Id | B1: category_id | C1: sub_category_id | D1: section_name | E1: section_tip | F1: status | G1: created_at
A2: 18 | B2: 1 | C2: 21 | D2: Indus Valley Civilization | F2: 1 | G2: 45907.452
A3: 19 | B3: 1 | C3: 21 | D3: Vedic Age | F3: 1 | G3: 45907.611
A4: 20 | B4: 1 | C4: 21 | D4: Mahajanapadas | F4: 1 | G4: 45907.612
A5: 21 | B5: 1 | C5: 21 | D5: Mauryan Empire | F5: 1 | G5: 45907.612
A6: 22 | B6: 1 | C6: 21 | D6: Post-Mauryan India (Sunga, Kushana, Gupta) | F6: 1 | G6: 45907.612
A7: 23 | B7: 1 | C7: 21 | D7: South Indian Dynasties (Sangam Age, Cholas, Cheras, Pandyas) | F7: 1 | G7: 45907.613
A8: 24 | B8: 1 | C8: 21 | D8: Religious Movements: Buddhism, Jainism | F8: 1 | G8: 45907.613
A9: 25 | B9: 1 | C9: 21 | D9: Art, Culture, and Architecture | F9: 1 | G9: 45907.613
A10: 26 | B10: 1 | C10: 2 | D10: Delhi Sultanate | F10: 1 | G10: 45907.627
A11: 27 | B11: 1 | C11: 2 | D11: Mughal Empire | F11: 1 | G11: 45907.627
A12: 28 | B12: 1 | C12: 2 | D12: Regional Kingdoms | F12: 1 | G12: 45907.627
A13: 29 | B13: 1 | C13: 2 | D13: Bhakti and Sufi Movements | F13: 1 | G13: 45907.628
... A103: 124 | B103: 11 | C103: 37 | D103: First Achievers | F103: 1 | G103: 45938.976
A104: 127 | B104: 13 | C104: 46 | D104: Percentage | E104: 1763094925_Screenshot2025-11-02at6.05.18P.jpeg | F104: 1 | G104: 45975.191
A105: 128 | B105: 13 | C105: 46 | D105: Profit & Loss | E105: 1763099489_24895956_b9cb653b-a9c9-477b-bb6f-627750effaad_lg.png | F105: 1 | G105: 45975.232
A106: 129 | B106: 13 | C106: 46 | D106: Simple & Compound Interest | E106: 1763185249_Screenshot 2025-11-15 110848.png | F106: 1 | G106: 45975.233
A107: 130 | B107: 13 | C107: 46 | D107: Ratio & Proportion | E107: 1763370744_Screenshot 2025-11-17 144145.png | F107: 1 | G107: 45975.233
A108: 131 | B108: 13 | C108: 46 | D108: Average | E108: 1763370796_Screenshot 2025-11-17 144236.png | F108: 1 | G108: 45975.233
A109: 132 | B109: 13 | C109: 46 | D109: Mixtures & Alligation | F109: 1 | G109: 45975.234
A110: 133 | B110: 13 | C110: 46 | D110: Time,Speed and Distance | F110: 1 | G110: 45975.235
A111: 134 | B111: 13 | C111: 46 | D111: Time & Work | F111: 1 | G111: 45975.236
A112: 135 | B112: 13 | C112: 46 | D112: Pipes & Cisterns | F112: 1 | G112: 45975.236
A113: 136 | B113: 13 | C113: 46 | D113: Partnership | E113: 1763799681_red-powder-isolated-white-background.png | F113: 1 | G113: 45975.236
A114: 137 | B114: 13 | C114: 46 | D114: Boats & Streams | E114: 1764064312_Screenshot 2025-11-25 152116.png | F114: 1 | G114: 45975.237
A115: 138 | B115: 13 | C115: 45 | D115: Linear & Quadratic Equations | E115: 1764048928_Screenshot 2025-11-25 110448.png | F115: 1 | G115: 45975.237
A116: 139 | B116: 13 | C116: 45 | D116: Inequalities | E116: 1764048976_Screenshot 2025-11-25 110520.png | F116: 1 | G116: 45975.238
A117: 140 | B117: 13 | C117: 45 | D117: Functions & Graphs | F117: 1 | G117: 45975.238
A118: 141 | B118: 13 | C118: 45 | D118: Sequences & Series | E118: 1764064732_Screenshot 2025-11-25 152814.png | F118: 1 | G118: 45975.238
A119: 142 | B119: 13 | C119: 45 | D119: Logarithms, Indices, and Surds | E119: 1764064788_Screenshot 2025-11-25 152850.png | F119: 1 | G119: 45975.239
A120: 143 | B120: 13 | C120: 47 | D120: Permutations & Combinations | E120: 1764166808_Untitled design.jpg | F120: 1 | G120: 45975.242
A121: 144 | B121: 13 | C121: 47 | D121: Probability | E121: 1764220985_Untitled design (1).jpg | F121: 1 | G121: 45975.243
A122: 145 | B122: 13 | C122: 47 | D122: Set Theory & Venn Diagrams | E122: 1764231462_Untitleddesign2.jpg | F122: 1 | G122: 45975.243
A123: 146 | B123: 15 | C123: 48 | D123: Coding-Decoding, Series, Analogies | E123: 1764309327_ChatGPT_Image_Nov_28_2025_11_20_16_AM (1).jpeg | F123: 1 | G123: 45975.252
A124: 147 | B124: 15 | C124: 48 | D124: Blood Relations | E124: 1764309869_Untitleddesign3.jpg | F124: 1 | G124: 45975.252
A125: 148 | B125: 15 | C125: 48 | D125: Direction Sense | E125: 1764488795_ChatGPT_Image_Nov_30_2025_01_11_22_PM (1).jpeg | F125: 1 | G125: 45975.254
A126: 149 | B126: 15 | C126: 48 | D126: Syllogisms, Logical Deductions | E126: 1764658251_Untitleddesign1.jpg | F126: 1 | G126: 45975.254
A127: 150 | B127: 15 | C127: 48 | D127: Seating Arrangements | E127: 1764661523_Untitleddesign2.jpg | F127: 1 | G127: 45975.255
A128: 151 | B128: 15 | C128: 48 | D128: Puzzles & Input-Output | F128: 1 | G128: 45975.256
A129: 152 | B129: 15 | C129: 48 | D129: Ranking and Ordering Problems | E129: 1764737274_Untitleddesign.jpg | F129: 1 | G129: 45975.256
A130: 153 | B130: 15 | C130: 49 | D130: Ethical Dilemmas & Situational Judgment | F130: 1 | G130: 45975.265
A131: 154 | B131: 15 | C131: 49 | D131: Administrative Decision Scenarios | F131: 1 | G131: 45975.265
A132: 155 | B132: 15 | C132: 49 | D132: Analytical Reasoning | F132: 1 | G132: 45975.266
A133: 156 | B133: 16 | C133: 50 | D133: Passages | F133: 1 | G133: 45975.267
A134: 157 | B134: 16 | C134: 50 | D134: Tone, Inference, and Central Idea | F134: 1 | G134: 45975.267
A135: 158 | B135: 16 | C135: 50 | D135: Vocabulary | F135: 1 | G135: 45975.267
A136: 159 | B136: 16 | C136: 50 | D136: Fact,Inference and Judgment | F136: 1 | G136: 45975.268
A137: 160 | B137: 16 | C137: 51 | D137: Para Summary | F137: 1 | G137: 45975.269
A138: 161 | B138: 16 | C138: 51 | D138: Odd Sentence | F138: 1 | G138: 45975.269
A139: 162 | B139: 16 | C139: 51 | D139: Sentence Correction & Grammar | F139: 1 | G139: 45975.271
A140: 163 | B140: 16 | C140: 51 | D140: Word Usage and Idioms | F140: 1 | G140: 45975.271
A141: 164 | B141: 11 | C141: 40 | D141: Dams, Rivers, Power Plants | F141: 1 | G141: 45992.369
